{"data":{"teamsInfo":{"away":{"hr":[],"hit":[10,95,107,116,187,232,241,286,330,388],"o":[5,17,59,66,71,100,123,192,196,228,238,247,270,275,336,339,345,384,395,433,438,450],"lineup":{"73703":{"balls":[95,232,336,450],"name":"한상훈"},"72860":{"balls":[100],"name":"이대수"},"74729":{"balls":[17,187,275,395],"name":"최진행"},"76753":{"balls":[71,228,330],"name":"송광민"},"62748":{"balls":[107,241,345],"name":"엄태용"},"71752":{"balls":[59,192,433],"name":"김태균"},"76746":{"balls":[66,196,286,438],"name":"김태완"},"72139":{"balls":[10,123,270,388],"name":"추승우"},"74148":{"balls":[238,339],"name":"이학준"},"74745":{"balls":[5,116,247,384],"name":"고동진"}}},"home":{"hr":[],"hit":[28,42,49,133,141,145,149,156,309,356],"o":[37,54,79,82,88,136,167,177,204,212,220,253,259,262,301,320,367,373,402,424],"lineup":{"73306":{"balls":[79,167,402],"name":"지석훈"},"78122":{"balls":[133,212],"name":"김태군"},"63963":{"balls":[54,156,262,373],"name":"권희동"},"62947":{"balls":[42,145,253,356],"name":"나성범"},"73543":{"balls":[320],"name":"박정준"},"94629":{"balls":[49,149,259,367],"name":"이호준"},"78813":{"balls":[37,141,220],"name":"모창민"},"77454":{"balls":[28,136],"name":"김종호"},"62931":{"balls":[88,204,309,424],"name":"노진혁"},"75441":{"balls":[82,177,301],"name":"조영훈"}}}},"ballsInfo":{"away":{"275":{"inn":"6회초","detailResult":"삼진 아웃","result":"아웃","seqno":275,"gy":0,"batterName":"최진행","gx":0,"pitcherName":"찰리"},"71":{"inn":"2회초","detailResult":"삼진 아웃","result":"아웃","seqno":71,"gy":0,"batterName":"송광민","gx":0,"pitcherName":"찰리"},"339":{"inn":"7회초","detailResult":"2루수 땅볼 아웃","result":"아웃","seqno":339,"gy":343,"batterName":"이학준","gx":309,"pitcherName":"찰리"},"5":{"inn":"1회초","detailResult":"유격수 땅볼 아웃","result":"아웃","seqno":5,"gy":337,"batterName":"고동진","gx":204,"pitcherName":"찰리"},"66":{"inn":"2회초","detailResult":"삼진 아웃","result":"아웃","seqno":66,"gy":0,"batterName":"김태완","gx":0,"pitcherName":"찰리"},"336":{"inn":"7회초","detailResult":"좌익수 플라이 아웃","result":"아웃","seqno":336,"gy":250,"batterName":"한상훈","gx":148,"pitcherName":"찰리"},"196":{"inn":"4회초","detailResult":"우익수 플라이 아웃","result":"아웃","seqno":196,"gy":231,"batterName":"김태완","gx":422,"pitcherName":"찰리"},"10":{"inn":"1회초","detailResult":"유격수 실책으로 출루","result":"안타","seqno":10,"gy":341,"batterName":"추승우","gx":223,"pitcherName":"찰리"},"192":{"inn":"4회초","detailResult":"유격수 병살타 아웃","result":"아웃","seqno":192,"gy":336,"batterName":"김태균","gx":218,"pitcherName":"찰리"},"286":{"inn":"6회초","detailResult":"3루수 앞 땅볼로 출루","result":"안타","seqno":286,"gy":378,"batterName":"김태완","gx":206,"pitcherName":"찰리"},"345":{"inn":"7회초","detailResult":"삼진 아웃","result":"아웃","seqno":345,"gy":0,"batterName":"엄태용","gx":0,"pitcherName":"찰리"},"395":{"inn":"8회초","detailResult":"3루수 병살타 아웃","result":"아웃","seqno":395,"gy":384,"batterName":"최진행","gx":187,"pitcherName":"찰리"},"17":{"inn":"1회초","detailResult":"삼진 아웃","result":"아웃","seqno":17,"gy":0,"batterName":"최진행","gx":0,"pitcherName":"찰리"},"95":{"inn":"3회초","detailResult":"좌익수 앞 1루타","result":"안타","seqno":95,"gy":265,"batterName":"한상훈","gx":156,"pitcherName":"찰리"},"384":{"inn":"8회초","detailResult":"2루수 땅볼 아웃","result":"아웃","seqno":384,"gy":338,"batterName":"고동진","gx":287,"pitcherName":"찰리"},"270":{"inn":"6회초","detailResult":"삼진 아웃","result":"아웃","seqno":270,"gy":0,"batterName":"추승우","gx":0,"pitcherName":"찰리"},"330":{"inn":"7회초","detailResult":"우익수 앞 1루타","result":"안타","seqno":330,"gy":270,"batterName":"송광민","gx":348,"pitcherName":"찰리"},"450":{"inn":"9회초","detailResult":"1루수 땅볼 아웃","result":"아웃","seqno":450,"gy":397,"batterName":"한상훈","gx":304,"pitcherName":"손민한"},"388":{"inn":"8회초","detailResult":"우익수 앞 1루타","result":"안타","seqno":388,"gy":275,"batterName":"추승우","gx":366,"pitcherName":"찰리"},"238":{"inn":"5회초","detailResult":"삼진 아웃","result":"아웃","seqno":238,"gy":0,"batterName":"이학준","gx":0,"pitcherName":"찰리"},"100":{"inn":"3회초","detailResult":"삼진 아웃","result":"아웃","seqno":100,"gy":0,"batterName":"이대수","gx":0,"pitcherName":"찰리"},"232":{"inn":"5회초","detailResult":"좌익수 앞 1루타","result":"안타","seqno":232,"gy":263,"batterName":"한상훈","gx":160,"pitcherName":"찰리"},"433":{"inn":"9회초","detailResult":"3루수 땅볼 아웃","result":"아웃","seqno":433,"gy":377,"batterName":"김태균","gx":199,"pitcherName":"손민한"},"228":{"inn":"5회초","detailResult":"삼진 아웃","result":"아웃","seqno":228,"gy":0,"batterName":"송광민","gx":0,"pitcherName":"찰리"},"107":{"inn":"3회초","detailResult":"우익수 앞 1루타","result":"안타","seqno":107,"gy":292,"batterName":"엄태용","gx":351,"pitcherName":"찰리"},"438":{"inn":"9회초","detailResult":"삼진 아웃","result":"아웃","seqno":438,"gy":0,"batterName":"김태완","gx":0,"pitcherName":"손민한"},"187":{"inn":"4회초","detailResult":"중견수 앞 1루타","result":"안타","seqno":187,"gy":235,"batterName":"최진행","gx":256,"pitcherName":"찰리"},"116":{"inn":"3회초","detailResult":"유격수 앞 땅볼로 출루","result":"안타","seqno":116,"gy":367,"batterName":"고동진","gx":230,"pitcherName":"찰리"},"59":{"inn":"2회초","detailResult":"우익수 플라이 아웃","result":"아웃","seqno":59,"gy":227,"batterName":"김태균","gx":375,"pitcherName":"찰리"},"247":{"inn":"5회초","detailResult":"유격수 땅볼 아웃","result":"아웃","seqno":247,"gy":359,"batterName":"고동진","gx":228,"pitcherName":"찰리"},"123":{"inn":"3회초","detailResult":"2루수 플라이 아웃","result":"아웃","seqno":123,"gy":288,"batterName":"추승우","gx":315,"pitcherName":"찰리"},"241":{"inn":"5회초","detailResult":"좌익수 왼쪽 2루타","result":"안타","seqno":241,"gy":213,"batterName":"엄태용","gx":85,"pitcherName":"찰리"}},"home":{"136":{"inn":"3회말","detailResult":"투수 희생번트 아웃","result":"아웃","seqno":136,"gy":425,"batterName":"김종호","gx":268,"pitcherName":"유창식"},"204":{"inn":"4회말","detailResult":"투수 땅볼 아웃","result":"아웃","seqno":204,"gy":399,"batterName":"노진혁","gx":253,"pitcherName":"유창식"},"141":{"inn":"3회말","detailResult":"좌익수 앞 1루타","result":"안타","seqno":141,"gy":257,"batterName":"모창민","gx":147,"pitcherName":"유창식"},"402":{"inn":"8회말","detailResult":"우익수 플라이 아웃","result":"아웃","seqno":402,"gy":269,"batterName":"지석훈","gx":358,"pitcherName":"송창식"},"79":{"inn":"2회말","detailResult":"포수 스트라이크 낫 아웃","result":"아웃","seqno":79,"gy":0,"batterName":"지석훈","gx":0,"pitcherName":"유창식"},"133":{"inn":"3회말","detailResult":"좌중간 2루타","result":"안타","seqno":133,"gy":155,"batterName":"김태군","gx":177,"pitcherName":"유창식"},"220":{"inn":"4회말","detailResult":"3루수 땅볼 아웃","result":"아웃","seqno":220,"gy":371,"batterName":"모창민","gx":199,"pitcherName":"유창식"},"259":{"inn":"5회말","detailResult":"3루수 땅볼 아웃","result":"아웃","seqno":259,"gy":377,"batterName":"이호준","gx":198,"pitcherName":"이태양"},"156":{"inn":"3회말","detailResult":"좌익수 앞 1루타","result":"안타","seqno":156,"gy":372,"batterName":"권희동","gx":184,"pitcherName":"유창식"},"262":{"inn":"5회말","detailResult":"좌익수 플라이 아웃","result":"아웃","seqno":262,"gy":228,"batterName":"권희동","gx":110,"pitcherName":"이태양"},"320":{"inn":"6회말","detailResult":"삼진 아웃","result":"아웃","seqno":320,"gy":0,"batterName":"박정준","gx":0,"pitcherName":"박정진"},"82":{"inn":"2회말","detailResult":"2루수 땅볼 아웃","result":"아웃","seqno":82,"gy":330,"batterName":"조영훈","gx":307,"pitcherName":"유창식"},"212":{"inn":"4회말","detailResult":"삼진 아웃","result":"아웃","seqno":212,"gy":0,"batterName":"김태군","gx":0,"pitcherName":"유창식"},"145":{"inn":"3회말","detailResult":"2루수 실책으로 출루","result":"안타","seqno":145,"gy":335,"batterName":"나성범","gx":303,"pitcherName":"유창식"},"149":{"inn":"3회말","detailResult":"중견수 왼쪽 1루타","result":"안타","seqno":149,"gy":225,"batterName":"이호준","gx":235,"pitcherName":"유창식"},"88":{"inn":"2회말","detailResult":"중견수 플라이 아웃","result":"아웃","seqno":88,"gy":193,"batterName":"노진혁","gx":295,"pitcherName":"유창식"},"28":{"inn":"1회말","detailResult":"중견수 왼쪽 1루타","result":"안타","seqno":28,"gy":234,"batterName":"김종호","gx":226,"pitcherName":"유창식"},"373":{"inn":"7회말","detailResult":"우익수 파울플라이 아웃","result":"아웃","seqno":373,"gy":294,"batterName":"권희동","gx":436,"pitcherName":"김광수"},"309":{"inn":"6회말","detailResult":"좌중간 2루타","result":"안타","seqno":309,"gy":160,"batterName":"노진혁","gx":175,"pitcherName":"이태양"},"37":{"inn":"1회말","detailResult":"삼진 아웃","result":"아웃","seqno":37,"gy":0,"batterName":"모창민","gx":0,"pitcherName":"유창식"},"42":{"inn":"1회말","detailResult":"좌익수 왼쪽 1루타","result":"안타","seqno":42,"gy":271,"batterName":"나성범","gx":85,"pitcherName":"유창식"},"167":{"inn":"3회말","detailResult":"유격수 땅볼 아웃","result":"아웃","seqno":167,"gy":362,"batterName":"지석훈","gx":220,"pitcherName":"유창식"},"356":{"inn":"7회말","detailResult":"2루수 앞 땅볼로 출루","result":"안타","seqno":356,"gy":356,"batterName":"나성범","gx":306,"pitcherName":"박정진"},"424":{"inn":"8회말","detailResult":"삼진 아웃","result":"아웃","seqno":424,"gy":0,"batterName":"노진혁","gx":0,"pitcherName":"송창식"},"49":{"inn":"1회말","detailResult":"유격수 앞 땅볼로 출루","result":"안타","seqno":49,"gy":339,"batterName":"이호준","gx":225,"pitcherName":"유창식"},"253":{"inn":"5회말","detailResult":"1루수 땅볼 아웃","result":"아웃","seqno":253,"gy":380,"batterName":"나성범","gx":318,"pitcherName":"이태양"},"54":{"inn":"1회말","detailResult":"중견수 플라이 아웃","result":"아웃","seqno":54,"gy":198,"batterName":"권희동","gx":275,"pitcherName":"유창식"},"367":{"inn":"7회말","detailResult":"삼진 아웃","result":"아웃","seqno":367,"gy":0,"batterName":"이호준","gx":0,"pitcherName":"김광수"},"177":{"inn":"3회말","detailResult":"우익수 플라이 아웃","result":"아웃","seqno":177,"gy":227,"batterName":"조영훈","gx":401,"pitcherName":"유창식"},"301":{"inn":"6회말","detailResult":"2루수 병살타 아웃","result":"아웃","seqno":301,"gy":324,"batterName":"조영훈","gx":278,"pitcherName":"이태양"}}}}}