{"data":{"teamsInfo":{"away":{"hr":[],"hit":[301,379,435,499,503,521],"o":[6,9,19,82,97,105,127,135,141,197,203,210,259,263,313,322,352,386,423,428,439,514,526],"lineup":{"73306":{"balls":[97,259,379],"name":"지석훈"},"78122":{"balls":[105,263],"name":"김태군"},"63963":{"balls":[82,210,503],"name":"권희동"},"62947":{"balls":[19,141,313,435],"name":"나성범"},"73543":{"balls":[521],"name":"박정준"},"94629":{"balls":[197,322,439],"name":"이호준"},"78813":{"balls":[203,352,499],"name":"모창민"},"77454":{"balls":[6,127,301,423],"name":"김종호"},"60102":{"balls":[526],"name":"이태원"},"62931":{"balls":[514],"name":"노진혁"},"63913":{"balls":[9,135,428],"name":"최재원"},"75441":{"balls":[386],"name":"조영훈"}}},"home":{"hr":[36],"hit":[49,155,231,238,268,341,464,469,484],"o":[27,31,57,111,114,119,174,182,190,218,224,246,275,278,293,331,337,344,394,403,411,456,478,491],"lineup":{"72443":{"balls":[36,174,275,403],"name":"최형우"},"74465":{"balls":[57,218,293,456],"name":"박석민"},"97202":{"balls":[469],"name":"진갑용"},"79402":{"balls":[119,238,341,478],"name":"김상수"},"77463":{"balls":[49,190],"name":"채태인"},"95436":{"balls":[182,278,411],"name":"이승엽"},"79456":{"balls":[114,231,337],"name":"이지영"},"73409":{"balls":[111,224,331,464],"name":"강명구"},"71432":{"balls":[31,268,394,491],"name":"박한이"},"79465":{"balls":[27,155,246,344,484],"name":"배영섭"}}}},"ballsInfo":{"away":{"141":{"inn":"3회초","detailResult":"좌익수 플라이 아웃","result":"아웃","seqno":141,"gy":247,"batterName":"나성범","gx":141,"pitcherName":"차우찬"},"203":{"inn":"4회초","detailResult":"유격수 땅볼 아웃","result":"아웃","seqno":203,"gy":311,"batterName":"모창민","gx":241,"pitcherName":"차우찬"},"6":{"inn":"1회초","detailResult":"삼진 아웃","result":"아웃","seqno":6,"gy":0,"batterName":"김종호","gx":0,"pitcherName":"차우찬"},"197":{"inn":"4회초","detailResult":"유격수 땅볼 아웃","result":"아웃","seqno":197,"gy":327,"batterName":"이호준","gx":211,"pitcherName":"차우찬"},"9":{"inn":"1회초","detailResult":"3루수 땅볼 아웃","result":"아웃","seqno":9,"gy":379,"batterName":"최재원","gx":186,"pitcherName":"차우찬"},"135":{"inn":"3회초","detailResult":"삼진 아웃","result":"아웃","seqno":135,"gy":0,"batterName":"최재원","gx":0,"pitcherName":"차우찬"},"259":{"inn":"5회초","detailResult":"2루수 플라이 아웃","result":"아웃","seqno":259,"gy":323,"batterName":"지석훈","gx":270,"pitcherName":"차우찬"},"19":{"inn":"1회초","detailResult":"삼진 아웃","result":"아웃","seqno":19,"gy":0,"batterName":"나성범","gx":0,"pitcherName":"차우찬"},"322":{"inn":"6회초","detailResult":"중견수 플라이 아웃","result":"아웃","seqno":322,"gy":223,"batterName":"이호준","gx":257,"pitcherName":"차우찬"},"263":{"inn":"5회초","detailResult":"3루수 병살타 아웃","result":"아웃","seqno":263,"gy":366,"batterName":"김태군","gx":193,"pitcherName":"차우찬"},"82":{"inn":"2회초","detailResult":"삼진 아웃","result":"아웃","seqno":82,"gy":0,"batterName":"권희동","gx":0,"pitcherName":"차우찬"},"386":{"inn":"7회초","detailResult":"우익수 플라이 아웃","result":"아웃","seqno":386,"gy":220,"batterName":"조영훈","gx":356,"pitcherName":"권혁"},"210":{"inn":"4회초","detailResult":"삼진 아웃","result":"아웃","seqno":210,"gy":0,"batterName":"권희동","gx":0,"pitcherName":"차우찬"},"514":{"inn":"9회초","detailResult":"삼진 아웃","result":"아웃","seqno":514,"gy":0,"batterName":"노진혁","gx":0,"pitcherName":"김희걸"},"97":{"inn":"2회초","detailResult":"삼진 아웃","result":"아웃","seqno":97,"gy":0,"batterName":"지석훈","gx":0,"pitcherName":"차우찬"},"313":{"inn":"6회초","detailResult":"투수 병살타 아웃","result":"아웃","seqno":313,"gy":404,"batterName":"나성범","gx":249,"pitcherName":"차우찬"},"526":{"inn":"9회초","detailResult":"유격수 땅볼 아웃","result":"아웃","seqno":526,"gy":372,"batterName":"이태원","gx":225,"pitcherName":"김희걸"},"503":{"inn":"9회초","detailResult":"3루수 앞 땅볼로 출루","result":"안타","seqno":503,"gy":359,"batterName":"권희동","gx":215,"pitcherName":"김희걸"},"435":{"inn":"8회초","detailResult":"투수 왼쪽 내야안타","result":"안타","seqno":435,"gy":430,"batterName":"나성범","gx":262,"pitcherName":"권혁"},"521":{"inn":"9회초","detailResult":"중견수 앞 1루타","result":"안타","seqno":521,"gy":241,"batterName":"박정준","gx":252,"pitcherName":"김희걸"},"379":{"inn":"7회초","detailResult":"3루수 앞 땅볼로 출루","result":"안타","seqno":379,"gy":384,"batterName":"지석훈","gx":193,"pitcherName":"심창민"},"105":{"inn":"2회초","detailResult":"유격수 땅볼 아웃","result":"아웃","seqno":105,"gy":362,"batterName":"김태군","gx":236,"pitcherName":"차우찬"},"439":{"inn":"8회초","detailResult":"중견수 플라이 아웃","result":"아웃","seqno":439,"gy":184,"batterName":"이호준","gx":266,"pitcherName":"안지만"},"499":{"inn":"9회초","detailResult":"우익수 앞 1루타","result":"안타","seqno":499,"gy":307,"batterName":"모창민","gx":342,"pitcherName":"김희걸"},"352":{"inn":"7회초","detailResult":"삼진 아웃","result":"아웃","seqno":352,"gy":0,"batterName":"모창민","gx":0,"pitcherName":"차우찬"},"428":{"inn":"8회초","detailResult":"삼진 아웃","result":"아웃","seqno":428,"gy":0,"batterName":"최재원","gx":0,"pitcherName":"권혁"},"127":{"inn":"3회초","detailResult":"삼진 아웃","result":"아웃","seqno":127,"gy":0,"batterName":"김종호","gx":0,"pitcherName":"차우찬"},"301":{"inn":"6회초","detailResult":"좌익수 앞 1루타","result":"안타","seqno":301,"gy":283,"batterName":"김종호","gx":162,"pitcherName":"차우찬"},"423":{"inn":"8회초","detailResult":"투수 땅볼 아웃","result":"아웃","seqno":423,"gy":407,"batterName":"김종호","gx":251,"pitcherName":"권혁"}},"home":{"478":{"inn":"8회말","detailResult":"유격수 땅볼 아웃","result":"아웃","seqno":478,"gy":354,"batterName":"김상수","gx":229,"pitcherName":"윤강민"},"275":{"inn":"5회말","detailResult":"중견수 플라이 아웃","result":"아웃","seqno":275,"gy":204,"batterName":"최형우","gx":277,"pitcherName":"이재학"},"411":{"inn":"7회말","detailResult":"삼진 아웃","result":"아웃","seqno":411,"gy":0,"batterName":"이승엽","gx":0,"pitcherName":"임창민"},"341":{"inn":"6회말","detailResult":"중견수 왼쪽 2루타","result":"안타","seqno":341,"gy":175,"batterName":"김상수","gx":237,"pitcherName":"이성민"},"278":{"inn":"5회말","detailResult":"좌익수 플라이 아웃","result":"아웃","seqno":278,"gy":251,"batterName":"이승엽","gx":132,"pitcherName":"이재학"},"337":{"inn":"6회말","detailResult":"3루수 땅볼 아웃","result":"아웃","seqno":337,"gy":376,"batterName":"이지영","gx":178,"pitcherName":"이성민"},"403":{"inn":"7회말","detailResult":"2루수 라인드라이브 아웃","result":"아웃","seqno":403,"gy":339,"batterName":"최형우","gx":296,"pitcherName":"임창민"},"469":{"inn":"8회말","detailResult":"좌익수 왼쪽 2루타","result":"안타","seqno":469,"gy":297,"batterName":"진갑용","gx":115,"pitcherName":"윤강민"},"464":{"inn":"8회말","detailResult":"좌익수 앞 1루타","result":"안타","seqno":464,"gy":316,"batterName":"강명구","gx":167,"pitcherName":"윤강민"},"344":{"inn":"6회말","detailResult":"우익수 플라이 아웃","result":"아웃","seqno":344,"gy":231,"batterName":"배영섭","gx":343,"pitcherName":"이성민"},"394":{"inn":"7회말","detailResult":"2루수 땅볼 아웃","result":"아웃","seqno":394,"gy":342,"batterName":"박한이","gx":290,"pitcherName":"임창민"},"155":{"inn":"3회말","detailResult":"중견수 뒤 2루타","result":"안타","seqno":155,"gy":159,"batterName":"배영섭","gx":260,"pitcherName":"이재학"},"218":{"inn":"4회말","detailResult":"3루수 땅볼 아웃","result":"아웃","seqno":218,"gy":387,"batterName":"박석민","gx":211,"pitcherName":"이재학"},"456":{"inn":"8회말","detailResult":"좌익수 플라이 아웃","result":"아웃","seqno":456,"gy":234,"batterName":"박석민","gx":120,"pitcherName":"윤강민"},"27":{"inn":"1회말","detailResult":"3루수 땅볼 아웃","result":"아웃","seqno":27,"gy":379,"batterName":"배영섭","gx":197,"pitcherName":"이재학"},"331":{"inn":"6회말","detailResult":"유격수 땅볼 아웃","result":"아웃","seqno":331,"gy":343,"batterName":"강명구","gx":212,"pitcherName":"이성민"},"31":{"inn":"1회말","detailResult":"중견수 플라이 아웃","result":"아웃","seqno":31,"gy":210,"batterName":"박한이","gx":278,"pitcherName":"이재학"},"268":{"inn":"5회말","detailResult":"우익수 앞 1루타","result":"안타","seqno":268,"gy":268,"batterName":"박한이","gx":387,"pitcherName":"이재학"},"238":{"inn":"4회말","detailResult":"중견수 앞 1루타","result":"안타","seqno":238,"gy":243,"batterName":"김상수","gx":266,"pitcherName":"이재학"},"174":{"inn":"3회말","detailResult":"삼진 아웃","result":"아웃","seqno":174,"gy":0,"batterName":"최형우","gx":0,"pitcherName":"이재학"},"36":{"inn":"1회말","detailResult":"중견수 뒤 홈런","result":"홈런","seqno":36,"gy":96,"batterName":"최형우","gx":263,"pitcherName":"이재학"},"231":{"inn":"4회말","detailResult":"2루수 왼쪽 내야안타","result":"안타","seqno":231,"gy":329,"batterName":"이지영","gx":280,"pitcherName":"이재학"},"111":{"inn":"2회말","detailResult":"1루수 라인드라이브 아웃","result":"아웃","seqno":111,"gy":364,"batterName":"강명구","gx":319,"pitcherName":"이재학"},"224":{"inn":"4회말","detailResult":"중견수 플라이 아웃","result":"아웃","seqno":224,"gy":219,"batterName":"강명구","gx":247,"pitcherName":"이재학"},"119":{"inn":"2회말","detailResult":"우익수 플라이 아웃","result":"아웃","seqno":119,"gy":249,"batterName":"김상수","gx":384,"pitcherName":"이재학"},"49":{"inn":"1회말","detailResult":"우중간 2루타","result":"안타","seqno":49,"gy":173,"batterName":"채태인","gx":363,"pitcherName":"이재학"},"190":{"inn":"3회말","detailResult":"삼진 아웃","result":"아웃","seqno":190,"gy":0,"batterName":"채태인","gx":0,"pitcherName":"이재학"},"114":{"inn":"2회말","detailResult":"3루수 땅볼 아웃","result":"아웃","seqno":114,"gy":378,"batterName":"이지영","gx":207,"pitcherName":"이재학"},"293":{"inn":"5회말","detailResult":"삼진 아웃","result":"아웃","seqno":293,"gy":0,"batterName":"박석민","gx":0,"pitcherName":"이재학"},"491":{"inn":"8회말","detailResult":"유격수 땅볼 아웃","result":"아웃","seqno":491,"gy":318,"batterName":"박한이","gx":234,"pitcherName":"윤강민"},"246":{"inn":"4회말","detailResult":"삼진 아웃","result":"아웃","seqno":246,"gy":0,"batterName":"배영섭","gx":0,"pitcherName":"이재학"},"484":{"inn":"8회말","detailResult":"중견수 왼쪽 1루타","result":"안타","seqno":484,"gy":252,"batterName":"배영섭","gx":233,"pitcherName":"윤강민"},"57":{"inn":"1회말","detailResult":"삼진 아웃","result":"아웃","seqno":57,"gy":0,"batterName":"박석민","gx":0,"pitcherName":"이재학"},"182":{"inn":"3회말","detailResult":"좌익수 희생플라이 아웃","result":"아웃","seqno":182,"gy":215,"batterName":"이승엽","gx":149,"pitcherName":"이재학"}}}}}