{"data":{"teamsInfo":{"away":{"hr":[148],"hit":[15,90,141,178,181,188,200,220,253,268,277,333,387,397,403],"o":[11,19,30,97,105,130,136,154,196,206,229,258,262,285,323,341,352,392,411,418,447,459,463,500,504,509],"lineup":{"72443":{"balls":[19,148,220,411],"name":"최형우"},"74465":{"balls":[90,181,258],"name":"박석민"},"97202":{"balls":[105,196,268,387,463],"name":"진갑용"},"77463":{"balls":[178,253,341,447],"name":"채태인"},"95436":{"balls":[30,154,229,333,418],"name":"이승엽"},"73409":{"balls":[97,188,262,352,459],"name":"강명구"},"71432":{"balls":[15,141,323,403,509],"name":"박한이"},"79459":{"balls":[11,136,206,285,397,504],"name":"정형식"},"61104":{"balls":[130,200,277,392,500],"name":"정병곤"}}},"home":{"hr":[235,482],"hit":[42,52,67,169,294,304,370,376,517],"o":[48,60,77,113,117,122,160,164,174,239,244,247,312,358,363,427,433,440,478,488,494,526,538,555],"lineup":{"79608":{"balls":[77,239,376,517],"name":"안치홍"},"74605":{"balls":[113,244,427,526],"name":"김주형"},"70612":{"balls":[117,247],"name":"김상훈"},"70756":{"balls":[67,235,370,494],"name":"이범호"},"62646":{"balls":[538],"name":"황정립"},"63634":{"balls":[433],"name":"이홍구"},"72559":{"balls":[52,169,358,482],"name":"신종길"},"78603":{"balls":[122,294,440],"name":"김선빈"},"78629":{"balls":[60,174,363,488],"name":"나지완"},"70410":{"balls":[48,164,312,478],"name":"김주찬"},"74163":{"balls":[42,160,304,555],"name":"이용규"}}}},"ballsInfo":{"away":{"411":{"inn":"7회초","detailResult":"삼진 아웃","result":"아웃","seqno":411,"gy":0,"batterName":"최형우","gx":0,"pitcherName":"신승현"},"136":{"inn":"3회초","detailResult":"1루수 땅볼 아웃","result":"아웃","seqno":136,"gy":374,"batterName":"정형식","gx":317,"pitcherName":"김진우"},"341":{"inn":"6회초","detailResult":"삼진 아웃","result":"아웃","seqno":341,"gy":0,"batterName":"채태인","gx":0,"pitcherName":"심동섭"},"206":{"inn":"4회초","detailResult":"중견수 플라이 아웃","result":"아웃","seqno":206,"gy":204,"batterName":"정형식","gx":284,"pitcherName":"김진우"},"141":{"inn":"3회초","detailResult":"우익수 앞 1루타","result":"안타","seqno":141,"gy":274,"batterName":"박한이","gx":365,"pitcherName":"김진우"},"200":{"inn":"4회초","detailResult":"3루수 앞 내야안타","result":"안타","seqno":200,"gy":414,"batterName":"정병곤","gx":219,"pitcherName":"김진우"},"277":{"inn":"5회초","detailResult":"좌익수 앞 1루타","result":"안타","seqno":277,"gy":274,"batterName":"정병곤","gx":160,"pitcherName":"박경태"},"403":{"inn":"7회초","detailResult":"좌익수 앞 1루타","result":"안타","seqno":403,"gy":316,"batterName":"박한이","gx":128,"pitcherName":"신승현"},"196":{"inn":"4회초","detailResult":"투수 희생번트 아웃","result":"아웃","seqno":196,"gy":434,"batterName":"진갑용","gx":251,"pitcherName":"김진우"},"130":{"inn":"3회초","detailResult":"삼진 아웃","result":"아웃","seqno":130,"gy":0,"batterName":"정병곤","gx":0,"pitcherName":"김진우"},"11":{"inn":"1회초","detailResult":"포수 스트라이크 낫 아웃","result":"아웃","seqno":11,"gy":0,"batterName":"정형식","gx":0,"pitcherName":"김진우"},"285":{"inn":"5회초","detailResult":"삼진 아웃","result":"아웃","seqno":285,"gy":0,"batterName":"정형식","gx":0,"pitcherName":"박경태"},"15":{"inn":"1회초","detailResult":"좌중간 2루타","result":"안타","seqno":15,"gy":188,"batterName":"박한이","gx":177,"pitcherName":"김진우"},"463":{"inn":"8회초","detailResult":"1루수 파울플라이 아웃","result":"아웃","seqno":463,"gy":388,"batterName":"진갑용","gx":404,"pitcherName":"오준형"},"220":{"inn":"4회초","detailResult":"우중간 2루타","result":"안타","seqno":220,"gy":157,"batterName":"최형우","gx":351,"pitcherName":"김진우"},"258":{"inn":"5회초","detailResult":"삼진 아웃","result":"아웃","seqno":258,"gy":0,"batterName":"박석민","gx":0,"pitcherName":"박경태"},"154":{"inn":"3회초","detailResult":"삼진 아웃","result":"아웃","seqno":154,"gy":0,"batterName":"이승엽","gx":0,"pitcherName":"김진우"},"19":{"inn":"1회초","detailResult":"2루수 땅볼 아웃","result":"아웃","seqno":19,"gy":330,"batterName":"최형우","gx":296,"pitcherName":"김진우"},"392":{"inn":"7회초","detailResult":"유격수 플라이 아웃","result":"아웃","seqno":392,"gy":308,"batterName":"정병곤","gx":231,"pitcherName":"신승현"},"459":{"inn":"8회초","detailResult":"삼진 아웃","result":"아웃","seqno":459,"gy":0,"batterName":"강명구","gx":0,"pitcherName":"오준형"},"262":{"inn":"5회초","detailResult":"중견수 플라이 아웃","result":"아웃","seqno":262,"gy":190,"batterName":"강명구","gx":273,"pitcherName":"박경태"},"323":{"inn":"6회초","detailResult":"좌익수 플라이 아웃","result":"아웃","seqno":323,"gy":200,"batterName":"박한이","gx":72,"pitcherName":"심동섭"},"397":{"inn":"7회초","detailResult":"중견수 오른쪽 1루타","result":"안타","seqno":397,"gy":258,"batterName":"정형식","gx":284,"pitcherName":"신승현"},"387":{"inn":"7회초","detailResult":"좌익수 왼쪽 2루타","result":"안타","seqno":387,"gy":274,"batterName":"진갑용","gx":78,"pitcherName":"신승현"},"333":{"inn":"6회초","detailResult":"우익수 앞 1루타","result":"안타","seqno":333,"gy":286,"batterName":"이승엽","gx":350,"pitcherName":"심동섭"},"148":{"inn":"3회초","detailResult":"우익수 뒤 홈런","result":"홈런","seqno":148,"gy":91,"batterName":"최형우","gx":495,"pitcherName":"김진우"},"268":{"inn":"5회초","detailResult":"우중간 1루타","result":"안타","seqno":268,"gy":225,"batterName":"진갑용","gx":345,"pitcherName":"박경태"},"90":{"inn":"2회초","detailResult":"좌익수 앞 1루타","result":"안타","seqno":90,"gy":289,"batterName":"박석민","gx":153,"pitcherName":"김진우"},"30":{"inn":"1회초","detailResult":"삼진 아웃","result":"아웃","seqno":30,"gy":0,"batterName":"이승엽","gx":0,"pitcherName":"김진우"},"509":{"inn":"9회초","detailResult":"우익수 플라이 아웃","result":"아웃","seqno":509,"gy":229,"batterName":"박한이","gx":385,"pitcherName":"오준형"},"504":{"inn":"9회초","detailResult":"3루수 파울플라이 아웃","result":"아웃","seqno":504,"gy":427,"batterName":"정형식","gx":111,"pitcherName":"오준형"},"447":{"inn":"8회초","detailResult":"우익수 플라이 아웃","result":"아웃","seqno":447,"gy":205,"batterName":"채태인","gx":372,"pitcherName":"오준형"},"97":{"inn":"2회초","detailResult":"투수 병살타 아웃","result":"아웃","seqno":97,"gy":404,"batterName":"강명구","gx":249,"pitcherName":"김진우"},"500":{"inn":"9회초","detailResult":"2루수 땅볼 아웃","result":"아웃","seqno":500,"gy":321,"batterName":"정병곤","gx":277,"pitcherName":"오준형"},"229":{"inn":"4회초","detailResult":"우익수 플라이 아웃","result":"아웃","seqno":229,"gy":219,"batterName":"이승엽","gx":378,"pitcherName":"박경태"},"105":{"inn":"2회초","detailResult":"삼진 아웃","result":"아웃","seqno":105,"gy":0,"batterName":"진갑용","gx":0,"pitcherName":"김진우"},"253":{"inn":"5회초","detailResult":"우익수 왼쪽 1루타","result":"안타","seqno":253,"gy":277,"batterName":"채태인","gx":355,"pitcherName":"박경태"},"352":{"inn":"6회초","detailResult":"3루수 땅볼 아웃","result":"아웃","seqno":352,"gy":379,"batterName":"강명구","gx":208,"pitcherName":"심동섭"},"188":{"inn":"4회초","detailResult":"좌익수 왼쪽 1루타","result":"안타","seqno":188,"gy":322,"batterName":"강명구","gx":136,"pitcherName":"김진우"},"178":{"inn":"4회초","detailResult":"좌익수 앞 1루타","result":"안타","seqno":178,"gy":275,"batterName":"채태인","gx":143,"pitcherName":"김진우"},"418":{"inn":"7회초","detailResult":"삼진 아웃","result":"아웃","seqno":418,"gy":0,"batterName":"이승엽","gx":0,"pitcherName":"신승현"},"181":{"inn":"4회초","detailResult":"좌익수 왼쪽 2루타","result":"안타","seqno":181,"gy":274,"batterName":"박석민","gx":79,"pitcherName":"김진우"}},"home":{"478":{"inn":"8회말","detailResult":"좌익수 플라이 아웃","result":"아웃","seqno":478,"gy":188,"batterName":"김주찬","gx":95,"pitcherName":"조현근"},"67":{"inn":"1회말","detailResult":"우익수 오른쪽 2루타","result":"안타","seqno":67,"gy":269,"batterName":"이범호","gx":425,"pitcherName":"장원삼"},"77":{"inn":"1회말","detailResult":"삼진 아웃","result":"아웃","seqno":77,"gy":0,"batterName":"안치홍","gx":0,"pitcherName":"장원삼"},"555":{"inn":"9회말","detailResult":"2루수 땅볼 아웃","result":"아웃","seqno":555,"gy":335,"batterName":"이용규","gx":295,"pitcherName":"오승환"},"440":{"inn":"7회말","detailResult":"1루수 파울플라이 아웃","result":"아웃","seqno":440,"gy":381,"batterName":"김선빈","gx":423,"pitcherName":"신용운"},"239":{"inn":"4회말","detailResult":"2루수 플라이 아웃","result":"아웃","seqno":239,"gy":295,"batterName":"안치홍","gx":315,"pitcherName":"장원삼"},"517":{"inn":"9회말","detailResult":"투수 앞 내야안타","result":"안타","seqno":517,"gy":402,"batterName":"안치홍","gx":248,"pitcherName":"오승환"},"304":{"inn":"5회말","detailResult":"우익수 앞 1루타","result":"안타","seqno":304,"gy":290,"batterName":"이용규","gx":336,"pitcherName":"장원삼"},"169":{"inn":"3회말","detailResult":"중견수 앞 1루타","result":"안타","seqno":169,"gy":213,"batterName":"신종길","gx":243,"pitcherName":"장원삼"},"235":{"inn":"4회말","detailResult":"좌중간 홈런","result":"홈런","seqno":235,"gy":93,"batterName":"이범호","gx":146,"pitcherName":"장원삼"},"174":{"inn":"3회말","detailResult":"우익수 플라이 아웃","result":"아웃","seqno":174,"gy":224,"batterName":"나지완","gx":387,"pitcherName":"장원삼"},"370":{"inn":"6회말","detailResult":"좌익수 앞 1루타","result":"안타","seqno":370,"gy":299,"batterName":"이범호","gx":164,"pitcherName":"장원삼"},"42":{"inn":"1회말","detailResult":"3루수 왼쪽 내야안타","result":"안타","seqno":42,"gy":376,"batterName":"이용규","gx":170,"pitcherName":"장원삼"},"433":{"inn":"7회말","detailResult":"삼진 아웃","result":"아웃","seqno":433,"gy":0,"batterName":"이홍구","gx":0,"pitcherName":"신용운"},"312":{"inn":"5회말","detailResult":"유격수 병살타 아웃","result":"아웃","seqno":312,"gy":325,"batterName":"김주찬","gx":248,"pitcherName":"장원삼"},"526":{"inn":"9회말","detailResult":"삼진 아웃","result":"아웃","seqno":526,"gy":0,"batterName":"김주형","gx":0,"pitcherName":"오승환"},"160":{"inn":"3회말","detailResult":"좌익수 플라이 아웃","result":"아웃","seqno":160,"gy":254,"batterName":"이용규","gx":121,"pitcherName":"장원삼"},"376":{"inn":"6회말","detailResult":"2루수 앞 땅볼로 출루","result":"안타","seqno":376,"gy":336,"batterName":"안치홍","gx":280,"pitcherName":"장원삼"},"164":{"inn":"3회말","detailResult":"좌익수 플라이 아웃","result":"아웃","seqno":164,"gy":258,"batterName":"김주찬","gx":148,"pitcherName":"장원삼"},"117":{"inn":"2회말","detailResult":"중견수 플라이 아웃","result":"아웃","seqno":117,"gy":217,"batterName":"김상훈","gx":305,"pitcherName":"장원삼"},"358":{"inn":"6회말","detailResult":"2루수 땅볼 아웃","result":"아웃","seqno":358,"gy":337,"batterName":"신종길","gx":292,"pitcherName":"장원삼"},"427":{"inn":"7회말","detailResult":"삼진 아웃","result":"아웃","seqno":427,"gy":0,"batterName":"김주형","gx":0,"pitcherName":"신용운"},"494":{"inn":"8회말","detailResult":"우익수 플라이 아웃","result":"아웃","seqno":494,"gy":229,"batterName":"이범호","gx":381,"pitcherName":"이동걸"},"48":{"inn":"1회말","detailResult":"삼진 아웃","result":"아웃","seqno":48,"gy":0,"batterName":"김주찬","gx":0,"pitcherName":"장원삼"},"488":{"inn":"8회말","detailResult":"유격수 땅볼 아웃","result":"아웃","seqno":488,"gy":342,"batterName":"나지완","gx":214,"pitcherName":"이동걸"},"113":{"inn":"2회말","detailResult":"유격수 땅볼 아웃","result":"아웃","seqno":113,"gy":334,"batterName":"김주형","gx":228,"pitcherName":"장원삼"},"294":{"inn":"5회말","detailResult":"우익수 앞 1루타","result":"안타","seqno":294,"gy":305,"batterName":"김선빈","gx":370,"pitcherName":"장원삼"},"52":{"inn":"1회말","detailResult":"좌익수 앞 1루타","result":"안타","seqno":52,"gy":286,"batterName":"신종길","gx":163,"pitcherName":"장원삼"},"247":{"inn":"4회말","detailResult":"우익수 플라이 아웃","result":"아웃","seqno":247,"gy":221,"batterName":"김상훈","gx":404,"pitcherName":"장원삼"},"244":{"inn":"4회말","detailResult":"삼진 아웃","result":"아웃","seqno":244,"gy":0,"batterName":"김주형","gx":0,"pitcherName":"장원삼"},"122":{"inn":"2회말","detailResult":"유격수 플라이 아웃","result":"아웃","seqno":122,"gy":291,"batterName":"김선빈","gx":173,"pitcherName":"장원삼"},"538":{"inn":"9회말","detailResult":"삼진 아웃","result":"아웃","seqno":538,"gy":0,"batterName":"황정립","gx":0,"pitcherName":"오승환"},"482":{"inn":"8회말","detailResult":"우익수 뒤 홈런","result":"홈런","seqno":482,"gy":124,"batterName":"신종길","gx":446,"pitcherName":"조현근"},"60":{"inn":"1회말","detailResult":"삼진 아웃","result":"아웃","seqno":60,"gy":0,"batterName":"나지완","gx":0,"pitcherName":"장원삼"},"363":{"inn":"6회말","detailResult":"유격수 플라이 아웃","result":"아웃","seqno":363,"gy":306,"batterName":"나지완","gx":210,"pitcherName":"장원삼"}}}}}