{"data":{"teamsInfo":{"away":{"hr":[227,269,273],"hit":[4,9,14,128,175,183,402],"o":[21,63,76,79,119,135,167,172,190,220,233,279,286,294,319,325,338,385,389],"lineup":{"73306":{"balls":[76,183,286,402],"name":"지석훈"},"78122":{"balls":[319],"name":"김태군"},"63963":{"balls":[63,172,273,389],"name":"권희동"},"62947":{"balls":[14,135,233,338],"name":"나성범"},"94629":{"balls":[21,167,269,385],"name":"이호준"},"78813":{"balls":[9,128,227],"name":"모창민"},"77454":{"balls":[4,119,220,325],"name":"김종호"},"62931":{"balls":[79,190,294],"name":"노진혁"},"75441":{"balls":[175,279],"name":"조영훈"}}},"home":{"hr":[],"hit":[42,50,260,303,369],"o":[29,36,54,87,91,102,144,153,158,196,200,206,242,256,265,298,309,312,343,362,376],"lineup":{"71837":{"balls":[91,242,343],"name":"김강민"},"75808":{"balls":[29,144,260,362],"name":"정근우"},"74846":{"balls":[50,196,303],"name":"박정권"},"71848":{"balls":[36,153,265,369],"name":"조동화"},"62895":{"balls":[87,206,312],"name":"한동민"},"75847":{"balls":[42,158,298,376],"name":"최정"},"98144":{"balls":[102,256],"name":"조인성"},"70646":{"balls":[54,200,309],"name":"김상현"}}}},"ballsInfo":{"away":{"273":{"inn":"6회초","detailResult":"좌중간 홈런","result":"홈런","seqno":273,"gy":96,"batterName":"권희동","gx":173,"pitcherName":"레이예스"},"4":{"inn":"1회초","detailResult":"중견수 앞 1루타","result":"안타","seqno":4,"gy":220,"batterName":"김종호","gx":226,"pitcherName":"레이예스"},"279":{"inn":"6회초","detailResult":"삼진 아웃","result":"아웃","seqno":279,"gy":0,"batterName":"조영훈","gx":0,"pitcherName":"레이예스"},"338":{"inn":"7회초","detailResult":"유격수 땅볼 아웃","result":"아웃","seqno":338,"gy":339,"batterName":"나성범","gx":216,"pitcherName":"진해수"},"402":{"inn":"8회초","detailResult":"유격수 앞 땅볼로 출루","result":"안타","seqno":402,"gy":337,"batterName":"지석훈","gx":214,"pitcherName":"임경완"},"76":{"inn":"2회초","detailResult":"유격수 플라이 아웃","result":"아웃","seqno":76,"gy":253,"batterName":"지석훈","gx":234,"pitcherName":"레이예스"},"128":{"inn":"3회초","detailResult":"3루수 실책으로 출루","result":"안타","seqno":128,"gy":377,"batterName":"모창민","gx":179,"pitcherName":"레이예스"},"9":{"inn":"1회초","detailResult":"우중간 1루타","result":"안타","seqno":9,"gy":222,"batterName":"모창민","gx":291,"pitcherName":"레이예스"},"79":{"inn":"2회초","detailResult":"1루수 땅볼 아웃","result":"아웃","seqno":79,"gy":363,"batterName":"노진혁","gx":293,"pitcherName":"레이예스"},"286":{"inn":"6회초","detailResult":"3루수 땅볼 아웃","result":"아웃","seqno":286,"gy":380,"batterName":"지석훈","gx":186,"pitcherName":"레이예스"},"135":{"inn":"3회초","detailResult":"3루수 땅볼 아웃","result":"아웃","seqno":135,"gy":376,"batterName":"나성범","gx":193,"pitcherName":"레이예스"},"14":{"inn":"1회초","detailResult":"투수 앞 땅볼로 출루","result":"안타","seqno":14,"gy":406,"batterName":"나성범","gx":263,"pitcherName":"레이예스"},"220":{"inn":"5회초","detailResult":"투수 병살타 아웃","result":"아웃","seqno":220,"gy":398,"batterName":"김종호","gx":248,"pitcherName":"레이예스"},"325":{"inn":"7회초","detailResult":"2루수 땅볼 아웃","result":"아웃","seqno":325,"gy":328,"batterName":"김종호","gx":293,"pitcherName":"레이예스"},"21":{"inn":"1회초","detailResult":"3루수 병살타 아웃","result":"아웃","seqno":21,"gy":378,"batterName":"이호준","gx":193,"pitcherName":"레이예스"},"385":{"inn":"8회초","detailResult":"2루수 플라이 아웃","result":"아웃","seqno":385,"gy":294,"batterName":"이호준","gx":315,"pitcherName":"진해수"},"389":{"inn":"8회초","detailResult":"3루수 땅볼 아웃","result":"아웃","seqno":389,"gy":384,"batterName":"권희동","gx":205,"pitcherName":"진해수"},"269":{"inn":"6회초","detailResult":"좌익수 뒤 홈런","result":"홈런","seqno":269,"gy":118,"batterName":"이호준","gx":72,"pitcherName":"레이예스"},"175":{"inn":"4회초","detailResult":"우익수 앞 1루타","result":"안타","seqno":175,"gy":243,"batterName":"조영훈","gx":361,"pitcherName":"레이예스"},"233":{"inn":"5회초","detailResult":"포수 스트라이크 낫 아웃","result":"아웃","seqno":233,"gy":0,"batterName":"나성범","gx":0,"pitcherName":"레이예스"},"172":{"inn":"4회초","detailResult":"삼진 아웃","result":"아웃","seqno":172,"gy":0,"batterName":"권희동","gx":0,"pitcherName":"레이예스"},"167":{"inn":"4회초","detailResult":"포수 스트라이크 낫 아웃","result":"아웃","seqno":167,"gy":0,"batterName":"이호준","gx":0,"pitcherName":"레이예스"},"227":{"inn":"5회초","detailResult":"중견수 뒤 홈런","result":"홈런","seqno":227,"gy":97,"batterName":"모창민","gx":283,"pitcherName":"레이예스"},"319":{"inn":"7회초","detailResult":"포수 스트라이크 낫 아웃","result":"아웃","seqno":319,"gy":0,"batterName":"김태군","gx":0,"pitcherName":"레이예스"},"119":{"inn":"3회초","detailResult":"삼진 아웃","result":"아웃","seqno":119,"gy":0,"batterName":"김종호","gx":0,"pitcherName":"레이예스"},"190":{"inn":"4회초","detailResult":"삼진 아웃","result":"아웃","seqno":190,"gy":0,"batterName":"노진혁","gx":0,"pitcherName":"레이예스"},"294":{"inn":"6회초","detailResult":"삼진 아웃","result":"아웃","seqno":294,"gy":0,"batterName":"노진혁","gx":0,"pitcherName":"레이예스"},"63":{"inn":"2회초","detailResult":"삼진 아웃","result":"아웃","seqno":63,"gy":0,"batterName":"권희동","gx":0,"pitcherName":"레이예스"},"183":{"inn":"4회초","detailResult":"좌익수 앞 1루타","result":"안타","seqno":183,"gy":242,"batterName":"지석훈","gx":168,"pitcherName":"레이예스"}},"home":{"343":{"inn":"7회말","detailResult":"좌익수 플라이 아웃","result":"아웃","seqno":343,"gy":193,"batterName":"김강민","gx":187,"pitcherName":"에릭"},"206":{"inn":"4회말","detailResult":"중견수 플라이 아웃","result":"아웃","seqno":206,"gy":176,"batterName":"한동민","gx":233,"pitcherName":"에릭"},"200":{"inn":"4회말","detailResult":"투수 땅볼 아웃","result":"아웃","seqno":200,"gy":401,"batterName":"김상현","gx":247,"pitcherName":"에릭"},"196":{"inn":"4회말","detailResult":"2루수 땅볼 아웃","result":"아웃","seqno":196,"gy":315,"batterName":"박정권","gx":296,"pitcherName":"에릭"},"153":{"inn":"3회말","detailResult":"2루수 땅볼 아웃","result":"아웃","seqno":153,"gy":320,"batterName":"조동화","gx":286,"pitcherName":"에릭"},"87":{"inn":"2회말","detailResult":"1루수 땅볼 아웃","result":"아웃","seqno":87,"gy":363,"batterName":"한동민","gx":312,"pitcherName":"에릭"},"256":{"inn":"5회말","detailResult":"1루수 파울플라이 아웃","result":"아웃","seqno":256,"gy":389,"batterName":"조인성","gx":356,"pitcherName":"에릭"},"158":{"inn":"3회말","detailResult":"우익수 플라이 아웃","result":"아웃","seqno":158,"gy":184,"batterName":"최정","gx":402,"pitcherName":"에릭"},"260":{"inn":"5회말","detailResult":"우익수 앞 1루타","result":"안타","seqno":260,"gy":256,"batterName":"정근우","gx":358,"pitcherName":"에릭"},"144":{"inn":"3회말","detailResult":"우익수 플라이 아웃","result":"아웃","seqno":144,"gy":218,"batterName":"정근우","gx":326,"pitcherName":"에릭"},"265":{"inn":"5회말","detailResult":"유격수 라인드라이브 아웃","result":"아웃","seqno":265,"gy":329,"batterName":"조동화","gx":221,"pitcherName":"에릭"},"29":{"inn":"1회말","detailResult":"삼진 아웃","result":"아웃","seqno":29,"gy":0,"batterName":"정근우","gx":0,"pitcherName":"에릭"},"91":{"inn":"2회말","detailResult":"2루수 땅볼 아웃","result":"아웃","seqno":91,"gy":340,"batterName":"김강민","gx":293,"pitcherName":"에릭"},"102":{"inn":"2회말","detailResult":"포수 스트라이크 낫 아웃","result":"아웃","seqno":102,"gy":0,"batterName":"조인성","gx":0,"pitcherName":"에릭"},"309":{"inn":"6회말","detailResult":"3루수 플라이 아웃","result":"아웃","seqno":309,"gy":380,"batterName":"김상현","gx":233,"pitcherName":"에릭"},"369":{"inn":"7회말","detailResult":"좌익수 앞 1루타","result":"안타","seqno":369,"gy":242,"batterName":"조동화","gx":173,"pitcherName":"손민한"},"36":{"inn":"1회말","detailResult":"포수 스트라이크 낫 아웃","result":"아웃","seqno":36,"gy":0,"batterName":"조동화","gx":0,"pitcherName":"에릭"},"42":{"inn":"1회말","detailResult":"중견수 앞 1루타","result":"안타","seqno":42,"gy":209,"batterName":"최정","gx":221,"pitcherName":"에릭"},"312":{"inn":"6회말","detailResult":"중견수 플라이 아웃","result":"아웃","seqno":312,"gy":163,"batterName":"한동민","gx":188,"pitcherName":"에릭"},"376":{"inn":"7회말","detailResult":"삼진 아웃","result":"아웃","seqno":376,"gy":0,"batterName":"최정","gx":0,"pitcherName":"손민한"},"50":{"inn":"1회말","detailResult":"중견수 앞 1루타","result":"안타","seqno":50,"gy":209,"batterName":"박정권","gx":225,"pitcherName":"에릭"},"54":{"inn":"1회말","detailResult":"투수 땅볼 아웃","result":"아웃","seqno":54,"gy":406,"batterName":"김상현","gx":245,"pitcherName":"에릭"},"298":{"inn":"6회말","detailResult":"좌익수 플라이 아웃","result":"아웃","seqno":298,"gy":190,"batterName":"최정","gx":170,"pitcherName":"에릭"},"242":{"inn":"5회말","detailResult":"좌익수 플라이 아웃","result":"아웃","seqno":242,"gy":181,"batterName":"김강민","gx":113,"pitcherName":"에릭"},"362":{"inn":"7회말","detailResult":"좌익수 플라이 아웃","result":"아웃","seqno":362,"gy":201,"batterName":"정근우","gx":88,"pitcherName":"손민한"},"303":{"inn":"6회말","detailResult":"중견수 앞 1루타","result":"안타","seqno":303,"gy":221,"batterName":"박정권","gx":284,"pitcherName":"에릭"}}}}}