{"data":{"teamsInfo":{"away":{"hr":[63,139],"hit":[80,143,192,205,285,291,340,349,355,360,422,497],"o":[8,16,76,96,103,127,136,148,211,227,276,282,300,334,369,418,429,434,493,502,510,601,609,614],"lineup":{"74605":{"balls":[143,282,369],"name":"김주형"},"62668":{"balls":[609],"name":"윤완주"},"75608":{"balls":[434],"name":"최훈락"},"74103":{"balls":[80,192,291,422],"name":"박기남"},"63634":{"balls":[429],"name":"이홍구"},"60667":{"balls":[76,148,285,418,601],"name":"이종환"},"79608":{"balls":[127,349,497],"name":"안치홍"},"70756":{"balls":[16,136,227,355,502],"name":"이범호"},"60605":{"balls":[96,205,334],"name":"홍재호"},"78643":{"balls":[300],"name":"백용환"},"72559":{"balls":[8,103,211,340,493],"name":"신종길"},"78629":{"balls":[63,139,276,360,510],"name":"나지완"},"73602":{"balls":[614],"name":"차일목"}}},"home":{"hr":[307],"hit":[155,179,231,245,253,383,391,449,468,516,524,533,543,551,558,564],"o":[24,36,56,108,114,121,162,169,184,238,269,317,326,388,401,408,443,457,485,538,575,581],"lineup":{"74540":{"balls":[114,238],"name":"강민호"},"99543":{"balls":[169,269],"name":"조성환"},"78513":{"balls":[179,443,533],"name":"전준우"},"63559":{"balls":[581],"name":"백민기"},"71815":{"balls":[401,516],"name":"박준서"},"71562":{"balls":[56,184,317,449,538],"name":"박종윤"},"62556":{"balls":[155,253,388,564],"name":"신본기"},"60523":{"balls":[121,245,383,468,558],"name":"정훈"},"74223":{"balls":[551],"name":"용덕한"},"72546":{"balls":[457,543],"name":"문규현"},"63593":{"balls":[24,162,391,485,575],"name":"조홍석"},"77532":{"balls":[36,307,408,524],"name":"손아섭"},"76313":{"balls":[108,231,326],"name":"황재균"}}}},"ballsInfo":{"away":{"205":{"inn":"4회초","detailResult":"투수 앞 땅볼로 출루","result":"안타","seqno":205,"gy":427,"batterName":"홍재호","gx":251,"pitcherName":"홍성민"},"136":{"inn":"3회초","detailResult":"유격수 플라이 아웃","result":"아웃","seqno":136,"gy":324,"batterName":"이범호","gx":194,"pitcherName":"옥스프링"},"139":{"inn":"3회초","detailResult":"우익수 뒤 홈런","result":"홈런","seqno":139,"gy":174,"batterName":"나지완","gx":499,"pitcherName":"옥스프링"},"609":{"inn":"9회초","detailResult":"삼진 아웃","result":"아웃","seqno":609,"gy":0,"batterName":"윤완주","gx":0,"pitcherName":"김성배"},"340":{"inn":"6회초","detailResult":"좌익수 앞 1루타","result":"안타","seqno":340,"gy":269,"batterName":"신종길","gx":174,"pitcherName":"김승회"},"614":{"inn":"9회초","detailResult":"3루수 라인드라이브 아웃","result":"아웃","seqno":614,"gy":370,"batterName":"차일목","gx":188,"pitcherName":"김성배"},"143":{"inn":"3회초","detailResult":"중견수 뒤 1루타","result":"안타","seqno":143,"gy":148,"batterName":"김주형","gx":205,"pitcherName":"옥스프링"},"276":{"inn":"5회초","detailResult":"좌익수 플라이 아웃","result":"아웃","seqno":276,"gy":205,"batterName":"나지완","gx":141,"pitcherName":"홍성민"},"76":{"inn":"2회초","detailResult":"중견수 플라이 아웃","result":"아웃","seqno":76,"gy":191,"batterName":"이종환","gx":251,"pitcherName":"옥스프링"},"8":{"inn":"1회초","detailResult":"포수 스트라이크 낫 아웃","result":"아웃","seqno":8,"gy":0,"batterName":"신종길","gx":0,"pitcherName":"옥스프링"},"282":{"inn":"5회초","detailResult":"2루수 땅볼 아웃","result":"아웃","seqno":282,"gy":338,"batterName":"김주형","gx":297,"pitcherName":"홍성민"},"349":{"inn":"6회초","detailResult":"중견수 앞 1루타","result":"안타","seqno":349,"gy":237,"batterName":"안치홍","gx":228,"pitcherName":"김승회"},"192":{"inn":"4회초","detailResult":"우익수 앞 1루타","result":"안타","seqno":192,"gy":271,"batterName":"박기남","gx":345,"pitcherName":"홍성민"},"285":{"inn":"5회초","detailResult":"우익수 앞 1루타","result":"안타","seqno":285,"gy":332,"batterName":"이종환","gx":318,"pitcherName":"홍성민"},"16":{"inn":"1회초","detailResult":"3루수 병살타 아웃","result":"아웃","seqno":16,"gy":381,"batterName":"이범호","gx":201,"pitcherName":"옥스프링"},"80":{"inn":"2회초","detailResult":"3루수 실책으로 출루","result":"안타","seqno":80,"gy":385,"batterName":"박기남","gx":198,"pitcherName":"옥스프링"},"334":{"inn":"6회초","detailResult":"3루수 땅볼 아웃","result":"아웃","seqno":334,"gy":377,"batterName":"홍재호","gx":202,"pitcherName":"김승회"},"148":{"inn":"3회초","detailResult":"2루수 땅볼 아웃","result":"아웃","seqno":148,"gy":342,"batterName":"이종환","gx":309,"pitcherName":"옥스프링"},"211":{"inn":"4회초","detailResult":"우익수 플라이 아웃","result":"아웃","seqno":211,"gy":234,"batterName":"신종길","gx":351,"pitcherName":"홍성민"},"103":{"inn":"2회초","detailResult":"좌익수 플라이 아웃","result":"아웃","seqno":103,"gy":223,"batterName":"신종길","gx":131,"pitcherName":"옥스프링"},"510":{"inn":"8회초","detailResult":"삼진 아웃","result":"아웃","seqno":510,"gy":0,"batterName":"나지완","gx":0,"pitcherName":"김성배"},"369":{"inn":"6회초","detailResult":"3루수 파울플라이 아웃","result":"아웃","seqno":369,"gy":431,"batterName":"김주형","gx":210,"pitcherName":"정대현"},"96":{"inn":"2회초","detailResult":"삼진 아웃","result":"아웃","seqno":96,"gy":0,"batterName":"홍재호","gx":0,"pitcherName":"옥스프링"},"502":{"inn":"8회초","detailResult":"좌익수 플라이 아웃","result":"아웃","seqno":502,"gy":215,"batterName":"이범호","gx":108,"pitcherName":"이명우"},"434":{"inn":"7회초","detailResult":"3루수 파울플라이 아웃","result":"아웃","seqno":434,"gy":435,"batterName":"최훈락","gx":160,"pitcherName":"정대현"},"227":{"inn":"4회초","detailResult":"3루수 땅볼 아웃","result":"아웃","seqno":227,"gy":372,"batterName":"이범호","gx":204,"pitcherName":"홍성민"},"497":{"inn":"8회초","detailResult":"중견수 앞 1루타","result":"안타","seqno":497,"gy":218,"batterName":"안치홍","gx":251,"pitcherName":"이명우"},"493":{"inn":"8회초","detailResult":"유격수 땅볼 아웃","result":"아웃","seqno":493,"gy":360,"batterName":"신종길","gx":234,"pitcherName":"이명우"},"291":{"inn":"5회초","detailResult":"우익수 앞 1루타","result":"안타","seqno":291,"gy":276,"batterName":"박기남","gx":356,"pitcherName":"홍성민"},"429":{"inn":"7회초","detailResult":"삼진 아웃","result":"아웃","seqno":429,"gy":0,"batterName":"이홍구","gx":0,"pitcherName":"정대현"},"355":{"inn":"6회초","detailResult":"좌익수 앞 1루타","result":"안타","seqno":355,"gy":236,"batterName":"이범호","gx":155,"pitcherName":"김승회"},"601":{"inn":"9회초","detailResult":"좌익수 플라이 아웃","result":"아웃","seqno":601,"gy":224,"batterName":"이종환","gx":102,"pitcherName":"김성배"},"127":{"inn":"3회초","detailResult":"우익수 플라이 아웃","result":"아웃","seqno":127,"gy":185,"batterName":"안치홍","gx":389,"pitcherName":"옥스프링"},"418":{"inn":"7회초","detailResult":"삼진 아웃","result":"아웃","seqno":418,"gy":0,"batterName":"이종환","gx":0,"pitcherName":"정대현"},"360":{"inn":"6회초","detailResult":"2루수 앞 땅볼로 출루","result":"안타","seqno":360,"gy":333,"batterName":"나지완","gx":279,"pitcherName":"정대현"},"63":{"inn":"2회초","detailResult":"좌익수 뒤 홈런","result":"홈런","seqno":63,"gy":169,"batterName":"나지완","gx":17,"pitcherName":"옥스프링"},"300":{"inn":"5회초","detailResult":"2루수 플라이 아웃","result":"아웃","seqno":300,"gy":306,"batterName":"백용환","gx":319,"pitcherName":"홍성민"},"422":{"inn":"7회초","detailResult":"좌익수 앞 1루타","result":"안타","seqno":422,"gy":278,"batterName":"박기남","gx":162,"pitcherName":"정대현"}},"home":{"551":{"inn":"8회말","detailResult":"좌익수 앞 1루타","result":"안타","seqno":551,"gy":264,"batterName":"용덕한","gx":177,"pitcherName":"박지훈"},"408":{"inn":"6회말","detailResult":"삼진 아웃","result":"아웃","seqno":408,"gy":0,"batterName":"손아섭","gx":0,"pitcherName":"손동욱"},"558":{"inn":"8회말","detailResult":"우중간 2루타","result":"안타","seqno":558,"gy":179,"batterName":"정훈","gx":397,"pitcherName":"박지훈"},"468":{"inn":"7회말","detailResult":"중견수 오른쪽 1루타","result":"안타","seqno":468,"gy":208,"batterName":"정훈","gx":281,"pitcherName":"신승현"},"401":{"inn":"6회말","detailResult":"삼진 아웃","result":"아웃","seqno":401,"gy":0,"batterName":"박준서","gx":0,"pitcherName":"손동욱"},"326":{"inn":"5회말","detailResult":"삼진 아웃","result":"아웃","seqno":326,"gy":0,"batterName":"황재균","gx":0,"pitcherName":"최향남"},"564":{"inn":"8회말","detailResult":"우익수 오른쪽 2루타","result":"안타","seqno":564,"gy":227,"batterName":"신본기","gx":463,"pitcherName":"박지훈"},"155":{"inn":"3회말","detailResult":"좌익수 앞 1루타","result":"안타","seqno":155,"gy":284,"batterName":"신본기","gx":174,"pitcherName":"박경태"},"457":{"inn":"7회말","detailResult":"2루수 땅볼 아웃","result":"아웃","seqno":457,"gy":337,"batterName":"문규현","gx":312,"pitcherName":"신승현"},"575":{"inn":"8회말","detailResult":"1루수 땅볼 아웃","result":"아웃","seqno":575,"gy":375,"batterName":"조홍석","gx":310,"pitcherName":"박지훈"},"24":{"inn":"1회말","detailResult":"투수 땅볼 아웃","result":"아웃","seqno":24,"gy":406,"batterName":"조홍석","gx":247,"pitcherName":"박경태"},"391":{"inn":"6회말","detailResult":"2루수 실책으로 출루","result":"안타","seqno":391,"gy":348,"batterName":"조홍석","gx":295,"pitcherName":"신창호"},"449":{"inn":"7회말","detailResult":"우익수 오른쪽 2루타","result":"안타","seqno":449,"gy":232,"batterName":"박종윤","gx":452,"pitcherName":"손동욱"},"269":{"inn":"4회말","detailResult":"3루수 땅볼 아웃","result":"아웃","seqno":269,"gy":366,"batterName":"조성환","gx":203,"pitcherName":"박경태"},"388":{"inn":"6회말","detailResult":"포수 파울플라이 아웃","result":"아웃","seqno":388,"gy":467,"batterName":"신본기","gx":251,"pitcherName":"신창호"},"516":{"inn":"8회말","detailResult":"좌익수 오른쪽 1루타","result":"안타","seqno":516,"gy":293,"batterName":"박준서","gx":153,"pitcherName":"박지훈"},"238":{"inn":"4회말","detailResult":"좌익수 플라이 아웃","result":"아웃","seqno":238,"gy":188,"batterName":"강민호","gx":120,"pitcherName":"박경태"},"169":{"inn":"3회말","detailResult":"1루수 파울플라이 아웃","result":"아웃","seqno":169,"gy":428,"batterName":"조성환","gx":381,"pitcherName":"박경태"},"307":{"inn":"5회말","detailResult":"우익수 뒤 홈런","result":"홈런","seqno":307,"gy":126,"batterName":"손아섭","gx":404,"pitcherName":"최향남"},"443":{"inn":"7회말","detailResult":"3루수 땅볼 아웃","result":"아웃","seqno":443,"gy":385,"batterName":"전준우","gx":184,"pitcherName":"손동욱"},"581":{"inn":"8회말","detailResult":"우익수 플라이 아웃","result":"아웃","seqno":581,"gy":258,"batterName":"백민기","gx":382,"pitcherName":"박지훈"},"36":{"inn":"1회말","detailResult":"중견수 플라이 아웃","result":"아웃","seqno":36,"gy":192,"batterName":"손아섭","gx":239,"pitcherName":"박경태"},"524":{"inn":"8회말","detailResult":"중견수 앞 1루타","result":"안타","seqno":524,"gy":228,"batterName":"손아섭","gx":253,"pitcherName":"박지훈"},"231":{"inn":"4회말","detailResult":"우익수 오른쪽 1루타","result":"안타","seqno":231,"gy":229,"batterName":"황재균","gx":408,"pitcherName":"박경태"},"162":{"inn":"3회말","detailResult":"삼진 아웃","result":"아웃","seqno":162,"gy":0,"batterName":"조홍석","gx":0,"pitcherName":"박경태"},"108":{"inn":"2회말","detailResult":"중견수 플라이 아웃","result":"아웃","seqno":108,"gy":182,"batterName":"황재균","gx":241,"pitcherName":"박경태"},"383":{"inn":"6회말","detailResult":"좌익수 앞 1루타","result":"안타","seqno":383,"gy":265,"batterName":"정훈","gx":175,"pitcherName":"신창호"},"317":{"inn":"5회말","detailResult":"좌익수 플라이 아웃","result":"아웃","seqno":317,"gy":209,"batterName":"박종윤","gx":138,"pitcherName":"최향남"},"533":{"inn":"8회말","detailResult":"좌익수 왼쪽 2루타","result":"안타","seqno":533,"gy":254,"batterName":"전준우","gx":50,"pitcherName":"박지훈"},"184":{"inn":"3회말","detailResult":"좌익수 플라이 아웃","result":"아웃","seqno":184,"gy":201,"batterName":"박종윤","gx":120,"pitcherName":"박경태"},"253":{"inn":"4회말","detailResult":"중견수 뒤 2루타","result":"안타","seqno":253,"gy":150,"batterName":"신본기","gx":287,"pitcherName":"박경태"},"114":{"inn":"2회말","detailResult":"삼진 아웃","result":"아웃","seqno":114,"gy":0,"batterName":"강민호","gx":0,"pitcherName":"박경태"},"485":{"inn":"7회말","detailResult":"삼진 아웃","result":"아웃","seqno":485,"gy":0,"batterName":"조홍석","gx":0,"pitcherName":"유동훈"},"179":{"inn":"3회말","detailResult":"우익수 뒤 3루타","result":"안타","seqno":179,"gy":190,"batterName":"전준우","gx":418,"pitcherName":"박경태"},"543":{"inn":"8회말","detailResult":"유격수 왼쪽 내야안타","result":"안타","seqno":543,"gy":334,"batterName":"문규현","gx":194,"pitcherName":"박지훈"},"56":{"inn":"1회말","detailResult":"3루수 파울플라이 아웃","result":"아웃","seqno":56,"gy":363,"batterName":"박종윤","gx":66,"pitcherName":"박경태"},"245":{"inn":"4회말","detailResult":"좌익수 왼쪽 1루타","result":"안타","seqno":245,"gy":238,"batterName":"정훈","gx":134,"pitcherName":"박경태"},"121":{"inn":"2회말","detailResult":"우익수 플라이 아웃","result":"아웃","seqno":121,"gy":218,"batterName":"정훈","gx":399,"pitcherName":"박경태"},"538":{"inn":"8회말","detailResult":"3루수 파울플라이 아웃","result":"아웃","seqno":538,"gy":401,"batterName":"박종윤","gx":140,"pitcherName":"박지훈"}}}}}