{"data":{"teamsInfo":{"away":{"hr":[],"hit":[3,69,73,199,300,465,473],"o":[9,13,18,59,66,80,132,144,152,181,185,248,256,259,286,292,312,350,358,364,388,403,454,460,487],"lineup":{"74465":{"balls":[59,181,292,403],"name":"박석민"},"95436":{"balls":[13,144,259,388],"name":"이승엽"},"71432":{"balls":[66,185,300,454],"name":"박한이"},"72466":{"balls":[9,132,256,364],"name":"조동찬"},"72443":{"balls":[18,152,286],"name":"최형우"},"71504":{"balls":[69,460],"name":"신명철"},"79402":{"balls":[80,350],"name":"김상수"},"97202":{"balls":[465],"name":"진갑용"},"77463":{"balls":[487],"name":"채태인"},"79456":{"balls":[73,199,312],"name":"이지영"},"74158":{"balls":[473],"name":"김태완"},"79465":{"balls":[3],"name":"배영섭"},"79459":{"balls":[248,358],"name":"정형식"}}},"home":{"hr":[439],"hit":[28,39,103,112,430],"o":[45,49,89,98,119,163,170,174,211,218,226,265,271,279,325,331,344,373,376,381,415,444],"lineup":{"73342":{"balls":[45,170,325],"name":"이택근"},"78168":{"balls":[28,279],"name":"서건창"},"74339":{"balls":[381],"name":"유한준"},"77243":{"balls":[112,265,376],"name":"허도환"},"77564":{"balls":[103,226,373],"name":"김민성"},"73136":{"balls":[98,218,344,444],"name":"이성열"},"79356":{"balls":[119,271],"name":"박헌도"},"75125":{"balls":[49,174,331,430],"name":"박병호"},"76325":{"balls":[89,211,439],"name":"강정호"},"71347":{"balls":[39,163,415],"name":"장기영"}}}},"ballsInfo":{"away":{"69":{"inn":"2회초","detailResult":"중견수 앞 1루타","result":"안타","seqno":69,"gy":254,"batterName":"신명철","gx":251,"pitcherName":"나이트"},"3":{"inn":"1회초","detailResult":"좌익수 앞 1루타","result":"안타","seqno":3,"gy":312,"batterName":"배영섭","gx":179,"pitcherName":"나이트"},"66":{"inn":"2회초","detailResult":"삼진 아웃","result":"아웃","seqno":66,"gy":0,"batterName":"박한이","gx":0,"pitcherName":"나이트"},"473":{"inn":"9회초","detailResult":"좌익수 앞 1루타","result":"안타","seqno":473,"gy":276,"batterName":"김태완","gx":157,"pitcherName":"손승락"},"403":{"inn":"8회초","detailResult":"유격수 병살타 아웃","result":"아웃","seqno":403,"gy":345,"batterName":"박석민","gx":229,"pitcherName":"이정훈"},"9":{"inn":"1회초","detailResult":"2루수 플라이 아웃","result":"아웃","seqno":9,"gy":324,"batterName":"조동찬","gx":284,"pitcherName":"나이트"},"350":{"inn":"7회초","detailResult":"유격수 땅볼 아웃","result":"아웃","seqno":350,"gy":351,"batterName":"김상수","gx":218,"pitcherName":"마정길"},"199":{"inn":"4회초","detailResult":"2루수 앞 땅볼로 출루","result":"안타","seqno":199,"gy":333,"batterName":"이지영","gx":265,"pitcherName":"나이트"},"132":{"inn":"3회초","detailResult":"투수 희생번트 아웃","result":"아웃","seqno":132,"gy":427,"batterName":"조동찬","gx":246,"pitcherName":"나이트"},"73":{"inn":"2회초","detailResult":"우익수 앞 1루타","result":"안타","seqno":73,"gy":279,"batterName":"이지영","gx":371,"pitcherName":"나이트"},"13":{"inn":"1회초","detailResult":"1루수 플라이 아웃","result":"아웃","seqno":13,"gy":426,"batterName":"이승엽","gx":253,"pitcherName":"나이트"},"286":{"inn":"6회초","detailResult":"삼진 아웃","result":"아웃","seqno":286,"gy":0,"batterName":"최형우","gx":0,"pitcherName":"나이트"},"465":{"inn":"9회초","detailResult":"우익수 앞 1루타","result":"안타","seqno":465,"gy":306,"batterName":"진갑용","gx":322,"pitcherName":"손승락"},"152":{"inn":"3회초","detailResult":"2루수 땅볼 아웃","result":"아웃","seqno":152,"gy":348,"batterName":"최형우","gx":280,"pitcherName":"나이트"},"259":{"inn":"5회초","detailResult":"투수 땅볼 아웃","result":"아웃","seqno":259,"gy":404,"batterName":"이승엽","gx":251,"pitcherName":"나이트"},"256":{"inn":"5회초","detailResult":"삼진 아웃","result":"아웃","seqno":256,"gy":0,"batterName":"조동찬","gx":0,"pitcherName":"나이트"},"460":{"inn":"9회초","detailResult":"삼진 아웃","result":"아웃","seqno":460,"gy":0,"batterName":"신명철","gx":0,"pitcherName":"손승락"},"18":{"inn":"1회초","detailResult":"유격수 땅볼 아웃","result":"아웃","seqno":18,"gy":378,"batterName":"최형우","gx":323,"pitcherName":"나이트"},"80":{"inn":"2회초","detailResult":"투수 땅볼 아웃","result":"아웃","seqno":80,"gy":407,"batterName":"김상수","gx":248,"pitcherName":"나이트"},"144":{"inn":"3회초","detailResult":"삼진 아웃","result":"아웃","seqno":144,"gy":0,"batterName":"이승엽","gx":0,"pitcherName":"나이트"},"454":{"inn":"9회초","detailResult":"2루수 땅볼 아웃","result":"아웃","seqno":454,"gy":352,"batterName":"박한이","gx":294,"pitcherName":"손승락"},"388":{"inn":"8회초","detailResult":"1루수 땅볼 아웃","result":"아웃","seqno":388,"gy":373,"batterName":"이승엽","gx":315,"pitcherName":"박성훈"},"312":{"inn":"6회초","detailResult":"유격수 땅볼 아웃","result":"아웃","seqno":312,"gy":335,"batterName":"이지영","gx":239,"pitcherName":"나이트"},"358":{"inn":"7회초","detailResult":"삼진 아웃","result":"아웃","seqno":358,"gy":0,"batterName":"정형식","gx":0,"pitcherName":"마정길"},"185":{"inn":"4회초","detailResult":"좌익수 플라이 아웃","result":"아웃","seqno":185,"gy":241,"batterName":"박한이","gx":131,"pitcherName":"나이트"},"292":{"inn":"6회초","detailResult":"유격수 땅볼 아웃","result":"아웃","seqno":292,"gy":357,"batterName":"박석민","gx":231,"pitcherName":"나이트"},"248":{"inn":"5회초","detailResult":"삼진 아웃","result":"아웃","seqno":248,"gy":0,"batterName":"정형식","gx":0,"pitcherName":"나이트"},"59":{"inn":"2회초","detailResult":"투수 땅볼 아웃","result":"아웃","seqno":59,"gy":418,"batterName":"박석민","gx":248,"pitcherName":"나이트"},"364":{"inn":"7회초","detailResult":"삼진 아웃","result":"아웃","seqno":364,"gy":0,"batterName":"조동찬","gx":0,"pitcherName":"마정길"},"487":{"inn":"9회초","detailResult":"삼진 아웃","result":"아웃","seqno":487,"gy":0,"batterName":"채태인","gx":0,"pitcherName":"손승락"},"300":{"inn":"6회초","detailResult":"투수 왼쪽 내야안타","result":"안타","seqno":300,"gy":436,"batterName":"박한이","gx":239,"pitcherName":"나이트"},"181":{"inn":"4회초","detailResult":"유격수 땅볼 아웃","result":"아웃","seqno":181,"gy":359,"batterName":"박석민","gx":235,"pitcherName":"나이트"}},"home":{"279":{"inn":"5회말","detailResult":"삼진 아웃","result":"아웃","seqno":279,"gy":0,"batterName":"서건창","gx":0,"pitcherName":"로드리게스"},"415":{"inn":"8회말","detailResult":"좌익수 플라이 아웃","result":"아웃","seqno":415,"gy":257,"batterName":"장기영","gx":137,"pitcherName":"안지만"},"344":{"inn":"6회말","detailResult":"2루수 땅볼 아웃","result":"아웃","seqno":344,"gy":345,"batterName":"이성열","gx":289,"pitcherName":"박근홍"},"325":{"inn":"6회말","detailResult":"유격수 플라이 아웃","result":"아웃","seqno":325,"gy":311,"batterName":"이택근","gx":229,"pitcherName":"로드리게스"},"218":{"inn":"4회말","detailResult":"포수 플라이 아웃","result":"아웃","seqno":218,"gy":447,"batterName":"이성열","gx":245,"pitcherName":"로드리게스"},"265":{"inn":"5회말","detailResult":"유격수 땅볼 아웃","result":"아웃","seqno":265,"gy":348,"batterName":"허도환","gx":233,"pitcherName":"로드리게스"},"89":{"inn":"2회말","detailResult":"좌익수 플라이 아웃","result":"아웃","seqno":89,"gy":214,"batterName":"강정호","gx":101,"pitcherName":"로드리게스"},"28":{"inn":"1회말","detailResult":"중견수 앞 1루타","result":"안타","seqno":28,"gy":245,"batterName":"서건창","gx":263,"pitcherName":"로드리게스"},"271":{"inn":"5회말","detailResult":"삼진 아웃","result":"아웃","seqno":271,"gy":0,"batterName":"박헌도","gx":0,"pitcherName":"로드리게스"},"331":{"inn":"6회말","detailResult":"우익수 플라이 아웃","result":"아웃","seqno":331,"gy":260,"batterName":"박병호","gx":399,"pitcherName":"로드리게스"},"211":{"inn":"4회말","detailResult":"3루수 땅볼 아웃","result":"아웃","seqno":211,"gy":390,"batterName":"강정호","gx":200,"pitcherName":"로드리게스"},"373":{"inn":"7회말","detailResult":"1루수 땅볼 아웃","result":"아웃","seqno":373,"gy":370,"batterName":"김민성","gx":318,"pitcherName":"심창민"},"170":{"inn":"3회말","detailResult":"1루수 파울플라이 아웃","result":"아웃","seqno":170,"gy":363,"batterName":"이택근","gx":419,"pitcherName":"로드리게스"},"103":{"inn":"2회말","detailResult":"중견수 앞 1루타","result":"안타","seqno":103,"gy":243,"batterName":"김민성","gx":273,"pitcherName":"로드리게스"},"444":{"inn":"8회말","detailResult":"2루수 플라이 아웃","result":"아웃","seqno":444,"gy":339,"batterName":"이성열","gx":316,"pitcherName":"안지만"},"98":{"inn":"2회말","detailResult":"투수 땅볼 아웃","result":"아웃","seqno":98,"gy":398,"batterName":"이성열","gx":280,"pitcherName":"로드리게스"},"174":{"inn":"3회말","detailResult":"2루수 땅볼 아웃","result":"아웃","seqno":174,"gy":340,"batterName":"박병호","gx":302,"pitcherName":"로드리게스"},"39":{"inn":"1회말","detailResult":"중견수 앞 1루타","result":"안타","seqno":39,"gy":269,"batterName":"장기영","gx":258,"pitcherName":"로드리게스"},"163":{"inn":"3회말","detailResult":"3루수 희생번트 아웃","result":"아웃","seqno":163,"gy":436,"batterName":"장기영","gx":242,"pitcherName":"로드리게스"},"381":{"inn":"7회말","detailResult":"삼진 아웃","result":"아웃","seqno":381,"gy":0,"batterName":"유한준","gx":0,"pitcherName":"심창민"},"226":{"inn":"4회말","detailResult":"삼진 아웃","result":"아웃","seqno":226,"gy":0,"batterName":"김민성","gx":0,"pitcherName":"로드리게스"},"376":{"inn":"7회말","detailResult":"2루수 땅볼 아웃","result":"아웃","seqno":376,"gy":347,"batterName":"허도환","gx":283,"pitcherName":"심창민"},"439":{"inn":"8회말","detailResult":"좌익수 뒤 홈런","result":"홈런","seqno":439,"gy":130,"batterName":"강정호","gx":92,"pitcherName":"안지만"},"45":{"inn":"1회말","detailResult":"2루수 플라이 아웃","result":"아웃","seqno":45,"gy":328,"batterName":"이택근","gx":325,"pitcherName":"로드리게스"},"119":{"inn":"2회말","detailResult":"삼진 아웃","result":"아웃","seqno":119,"gy":0,"batterName":"박헌도","gx":0,"pitcherName":"로드리게스"},"49":{"inn":"1회말","detailResult":"우익수 플라이 아웃","result":"아웃","seqno":49,"gy":291,"batterName":"박병호","gx":363,"pitcherName":"로드리게스"},"430":{"inn":"8회말","detailResult":"3루수 앞 땅볼로 출루","result":"안타","seqno":430,"gy":372,"batterName":"박병호","gx":202,"pitcherName":"안지만"},"112":{"inn":"2회말","detailResult":"좌익수 왼쪽 1루타","result":"안타","seqno":112,"gy":336,"batterName":"허도환","gx":170,"pitcherName":"로드리게스"}}}}}