{"data":{"teamsInfo":{"away":{"hr":[],"hit":[14,53,111,117,253,264,294,322,392,512,557],"o":[9,18,25,59,70,92,128,136,191,199,202,281,325,334,346,377,404,434,444,448,474,481,486,508,553],"lineup":{"76249":{"balls":[14,111,264,346,481],"name":"민병헌"},"75566":{"balls":[508],"name":"이원석"},"79240":{"balls":[191,322,434],"name":"허경민"},"77248":{"balls":[59,294,404],"name":"오재원"},"73213":{"balls":[92,202,334,448,553],"name":"손시헌"},"76290":{"balls":[18,117,377,486],"name":"김현수"},"99222":{"balls":[53,136,392,512],"name":"홍성흔"},"98218":{"balls":[25,128,281],"name":"김동주"},"73339":{"balls":[9,253,474,557],"name":"이종욱"},"76232":{"balls":[70,199,325,444],"name":"양의지"}}},"home":{"hr":[42],"hit":[31,81,143,154,209,223,235,354,417,571],"o":[37,49,78,85,151,161,170,229,242,300,305,312,359,371,409,424,428,452,460,469,491,496,502,580,586,594],"lineup":{"96761":{"balls":[586],"name":"송지만"},"71835":{"balls":[242],"name":"조중근"},"77243":{"balls":[151],"name":"허도환"},"79365":{"balls":[417,571],"name":"박동원"},"75125":{"balls":[49,209,354,460],"name":"박병호"},"71347":{"balls":[37,161,305,428],"name":"장기영"},"72303":{"balls":[580],"name":"김민우"},"78168":{"balls":[31,154,300,424],"name":"서건창"},"73342":{"balls":[42,170,312,452,594],"name":"이택근"},"77564":{"balls":[85,229,371,496],"name":"김민성"},"74339":{"balls":[143,235,409,502],"name":"유한준"},"73136":{"balls":[81,223,491],"name":"이성열"},"76325":{"balls":[78,359,469],"name":"강정호"}}}},"ballsInfo":{"away":{"136":{"inn":"3회초","detailResult":"삼진 아웃","result":"아웃","seqno":136,"gy":0,"batterName":"홍성흔","gx":0,"pitcherName":"강윤구"},"70":{"inn":"2회초","detailResult":"유격수 병살타 아웃","result":"아웃","seqno":70,"gy":340,"batterName":"양의지","gx":216,"pitcherName":"강윤구"},"474":{"inn":"9회초","detailResult":"유격수 플라이 아웃","result":"아웃","seqno":474,"gy":282,"batterName":"이종욱","gx":229,"pitcherName":"이정훈"},"202":{"inn":"4회초","detailResult":"중견수 플라이 아웃","result":"아웃","seqno":202,"gy":204,"batterName":"손시헌","gx":265,"pitcherName":"강윤구"},"128":{"inn":"3회초","detailResult":"중견수 플라이 아웃","result":"아웃","seqno":128,"gy":209,"batterName":"김동주","gx":256,"pitcherName":"강윤구"},"9":{"inn":"1회초","detailResult":"좌익수 플라이 아웃","result":"아웃","seqno":9,"gy":267,"batterName":"이종욱","gx":153,"pitcherName":"강윤구"},"199":{"inn":"4회초","detailResult":"좌익수 플라이 아웃","result":"아웃","seqno":199,"gy":213,"batterName":"양의지","gx":119,"pitcherName":"강윤구"},"281":{"inn":"5회초","detailResult":"2루수 플라이 아웃","result":"아웃","seqno":281,"gy":329,"batterName":"김동주","gx":359,"pitcherName":"송신영"},"557":{"inn":"10회초","detailResult":"중견수 오른쪽 1루타","result":"안타","seqno":557,"gy":260,"batterName":"이종욱","gx":291,"pitcherName":"손승락"},"346":{"inn":"6회초","detailResult":"우익수 파울플라이 아웃","result":"아웃","seqno":346,"gy":294,"batterName":"민병헌","gx":440,"pitcherName":"마정길"},"404":{"inn":"7회초","detailResult":"삼진 아웃","result":"아웃","seqno":404,"gy":0,"batterName":"오재원","gx":0,"pitcherName":"박성훈"},"14":{"inn":"1회초","detailResult":"우중간 3루타","result":"안타","seqno":14,"gy":157,"batterName":"민병헌","gx":293,"pitcherName":"강윤구"},"553":{"inn":"10회초","detailResult":"삼진 아웃","result":"아웃","seqno":553,"gy":0,"batterName":"손시헌","gx":0,"pitcherName":"손승락"},"18":{"inn":"1회초","detailResult":"좌익수 희생플라이 아웃","result":"아웃","seqno":18,"gy":271,"batterName":"김현수","gx":89,"pitcherName":"강윤구"},"325":{"inn":"6회초","detailResult":"투수 희생번트 아웃","result":"아웃","seqno":325,"gy":426,"batterName":"양의지","gx":259,"pitcherName":"마정길"},"392":{"inn":"7회초","detailResult":"유격수 왼쪽 내야안타","result":"안타","seqno":392,"gy":325,"batterName":"홍성흔","gx":187,"pitcherName":"마정길"},"322":{"inn":"6회초","detailResult":"좌중간 1루타","result":"안타","seqno":322,"gy":262,"batterName":"허경민","gx":200,"pitcherName":"마정길"},"25":{"inn":"1회초","detailResult":"포수 스트라이크 낫 아웃","result":"아웃","seqno":25,"gy":0,"batterName":"김동주","gx":0,"pitcherName":"강윤구"},"334":{"inn":"6회초","detailResult":"좌익수 플라이 아웃","result":"아웃","seqno":334,"gy":249,"batterName":"손시헌","gx":141,"pitcherName":"마정길"},"92":{"inn":"3회초","detailResult":"1루수 파울플라이 아웃","result":"아웃","seqno":92,"gy":417,"batterName":"손시헌","gx":319,"pitcherName":"강윤구"},"264":{"inn":"5회초","detailResult":"유격수 앞 땅볼로 출루","result":"안타","seqno":264,"gy":339,"batterName":"민병헌","gx":215,"pitcherName":"송신영"},"448":{"inn":"8회초","detailResult":"유격수 땅볼 아웃","result":"아웃","seqno":448,"gy":321,"batterName":"손시헌","gx":249,"pitcherName":"한현희"},"508":{"inn":"10회초","detailResult":"2루수 땅볼 아웃","result":"아웃","seqno":508,"gy":336,"batterName":"이원석","gx":277,"pitcherName":"손승락"},"512":{"inn":"10회초","detailResult":"중견수 오른쪽 1루타","result":"안타","seqno":512,"gy":253,"batterName":"홍성흔","gx":303,"pitcherName":"손승락"},"444":{"inn":"8회초","detailResult":"우익수 플라이 아웃","result":"아웃","seqno":444,"gy":247,"batterName":"양의지","gx":389,"pitcherName":"한현희"},"111":{"inn":"3회초","detailResult":"우중간 2루타","result":"안타","seqno":111,"gy":156,"batterName":"민병헌","gx":379,"pitcherName":"강윤구"},"434":{"inn":"8회초","detailResult":"3루수 땅볼 아웃","result":"아웃","seqno":434,"gy":396,"batterName":"허경민","gx":211,"pitcherName":"한현희"},"377":{"inn":"7회초","detailResult":"우익수 플라이 아웃","result":"아웃","seqno":377,"gy":242,"batterName":"김현수","gx":365,"pitcherName":"마정길"},"117":{"inn":"3회초","detailResult":"1루수 앞 땅볼로 출루","result":"안타","seqno":117,"gy":356,"batterName":"김현수","gx":307,"pitcherName":"강윤구"},"253":{"inn":"5회초","detailResult":"1루수 앞 내야안타","result":"안타","seqno":253,"gy":360,"batterName":"이종욱","gx":320,"pitcherName":"강윤구"},"191":{"inn":"4회초","detailResult":"삼진 아웃","result":"아웃","seqno":191,"gy":0,"batterName":"허경민","gx":0,"pitcherName":"강윤구"},"53":{"inn":"2회초","detailResult":"좌익수 앞 1루타","result":"안타","seqno":53,"gy":274,"batterName":"홍성흔","gx":151,"pitcherName":"강윤구"},"294":{"inn":"5회초","detailResult":"유격수 앞 땅볼로 출루","result":"안타","seqno":294,"gy":330,"batterName":"오재원","gx":210,"pitcherName":"송신영"},"59":{"inn":"2회초","detailResult":"3루수 플라이 아웃","result":"아웃","seqno":59,"gy":377,"batterName":"오재원","gx":243,"pitcherName":"강윤구"},"486":{"inn":"9회초","detailResult":"좌익수 플라이 아웃","result":"아웃","seqno":486,"gy":236,"batterName":"김현수","gx":134,"pitcherName":"이정훈"},"481":{"inn":"9회초","detailResult":"삼진 아웃","result":"아웃","seqno":481,"gy":0,"batterName":"민병헌","gx":0,"pitcherName":"이정훈"}},"home":{"409":{"inn":"7회말","detailResult":"우익수 플라이 아웃","result":"아웃","seqno":409,"gy":234,"batterName":"유한준","gx":388,"pitcherName":"오현택"},"143":{"inn":"3회말","detailResult":"좌익수 앞 1루타","result":"안타","seqno":143,"gy":311,"batterName":"유한준","gx":156,"pitcherName":"김상현"},"78":{"inn":"2회말","detailResult":"삼진 아웃","result":"아웃","seqno":78,"gy":0,"batterName":"강정호","gx":0,"pitcherName":"김상현"},"469":{"inn":"8회말","detailResult":"삼진 아웃","result":"아웃","seqno":469,"gy":0,"batterName":"강정호","gx":0,"pitcherName":"오현택"},"85":{"inn":"2회말","detailResult":"유격수 병살타 아웃","result":"아웃","seqno":85,"gy":341,"batterName":"김민성","gx":213,"pitcherName":"김상현"},"154":{"inn":"3회말","detailResult":"우익수 앞 1루타","result":"안타","seqno":154,"gy":291,"batterName":"서건창","gx":333,"pitcherName":"김상현"},"460":{"inn":"8회말","detailResult":"좌익수 플라이 아웃","result":"아웃","seqno":460,"gy":242,"batterName":"박병호","gx":149,"pitcherName":"오현택"},"223":{"inn":"4회말","detailResult":"투수 희생번트 실책으로 출루","result":"안타","seqno":223,"gy":432,"batterName":"이성열","gx":241,"pitcherName":"김상현"},"81":{"inn":"2회말","detailResult":"중견수 앞 1루타","result":"안타","seqno":81,"gy":245,"batterName":"이성열","gx":282,"pitcherName":"김상현"},"452":{"inn":"8회말","detailResult":"유격수 땅볼 아웃","result":"아웃","seqno":452,"gy":333,"batterName":"이택근","gx":206,"pitcherName":"오현택"},"571":{"inn":"10회말","detailResult":"좌익수 앞 2루타","result":"안타","seqno":571,"gy":264,"batterName":"박동원","gx":155,"pitcherName":"유희관"},"209":{"inn":"4회말","detailResult":"좌익수 앞 1루타","result":"안타","seqno":209,"gy":269,"batterName":"박병호","gx":152,"pitcherName":"김상현"},"31":{"inn":"1회말","detailResult":"2루수 실책으로 출루","result":"안타","seqno":31,"gy":312,"batterName":"서건창","gx":289,"pitcherName":"김상현"},"151":{"inn":"3회말","detailResult":"삼진 아웃","result":"아웃","seqno":151,"gy":0,"batterName":"허도환","gx":0,"pitcherName":"김상현"},"305":{"inn":"5회말","detailResult":"우익수 플라이 아웃","result":"아웃","seqno":305,"gy":199,"batterName":"장기영","gx":345,"pitcherName":"김상현"},"170":{"inn":"3회말","detailResult":"좌익수 플라이 아웃","result":"아웃","seqno":170,"gy":185,"batterName":"이택근","gx":109,"pitcherName":"김상현"},"580":{"inn":"10회말","detailResult":"삼진 아웃","result":"아웃","seqno":580,"gy":0,"batterName":"김민우","gx":0,"pitcherName":"유희관"},"235":{"inn":"4회말","detailResult":"우익수 오른쪽 1루타","result":"안타","seqno":235,"gy":296,"batterName":"유한준","gx":372,"pitcherName":"김상현"},"371":{"inn":"6회말","detailResult":"2루수 병살타 아웃","result":"아웃","seqno":371,"gy":333,"batterName":"김민성","gx":278,"pitcherName":"오현택"},"37":{"inn":"1회말","detailResult":"좌익수 플라이 아웃","result":"아웃","seqno":37,"gy":236,"batterName":"장기영","gx":126,"pitcherName":"김상현"},"42":{"inn":"1회말","detailResult":"좌익수 뒤 홈런","result":"홈런","seqno":42,"gy":113,"batterName":"이택근","gx":55,"pitcherName":"김상현"},"312":{"inn":"5회말","detailResult":"3루수 파울플라이 아웃","result":"아웃","seqno":312,"gy":389,"batterName":"이택근","gx":176,"pitcherName":"김상현"},"586":{"inn":"10회말","detailResult":"2루수 플라이 아웃","result":"아웃","seqno":586,"gy":255,"batterName":"송지만","gx":276,"pitcherName":"유희관"},"502":{"inn":"9회말","detailResult":"좌익수 플라이 아웃","result":"아웃","seqno":502,"gy":265,"batterName":"유한준","gx":153,"pitcherName":"오현택"},"161":{"inn":"3회말","detailResult":"우익수 플라이 아웃","result":"아웃","seqno":161,"gy":196,"batterName":"장기영","gx":374,"pitcherName":"김상현"},"229":{"inn":"4회말","detailResult":"포수 파울플라이 아웃","result":"아웃","seqno":229,"gy":475,"batterName":"김민성","gx":317,"pitcherName":"김상현"},"496":{"inn":"9회말","detailResult":"중견수 플라이 아웃","result":"아웃","seqno":496,"gy":211,"batterName":"김민성","gx":282,"pitcherName":"오현택"},"424":{"inn":"7회말","detailResult":"삼진 아웃","result":"아웃","seqno":424,"gy":0,"batterName":"서건창","gx":0,"pitcherName":"오현택"},"49":{"inn":"1회말","detailResult":"삼진 아웃","result":"아웃","seqno":49,"gy":0,"batterName":"박병호","gx":0,"pitcherName":"김상현"},"594":{"inn":"10회말","detailResult":"포수 파울플라이 아웃","result":"아웃","seqno":594,"gy":482,"batterName":"이택근","gx":250,"pitcherName":"유희관"},"359":{"inn":"6회말","detailResult":"유격수 땅볼 아웃","result":"아웃","seqno":359,"gy":348,"batterName":"강정호","gx":205,"pitcherName":"오현택"},"428":{"inn":"7회말","detailResult":"2루수 땅볼 아웃","result":"아웃","seqno":428,"gy":336,"batterName":"장기영","gx":333,"pitcherName":"오현택"},"491":{"inn":"9회말","detailResult":"1루수 라인드라이브 아웃","result":"아웃","seqno":491,"gy":365,"batterName":"이성열","gx":330,"pitcherName":"오현택"},"354":{"inn":"6회말","detailResult":"중견수 뒤 2루타","result":"안타","seqno":354,"gy":119,"batterName":"박병호","gx":223,"pitcherName":"김상현"},"417":{"inn":"7회말","detailResult":"3루수 실책으로 출루","result":"안타","seqno":417,"gy":370,"batterName":"박동원","gx":191,"pitcherName":"오현택"},"242":{"inn":"4회말","detailResult":"유격수 병살타 아웃","result":"아웃","seqno":242,"gy":334,"batterName":"조중근","gx":234,"pitcherName":"김상현"},"300":{"inn":"5회말","detailResult":"1루수 플라이 아웃","result":"아웃","seqno":300,"gy":365,"batterName":"서건창","gx":297,"pitcherName":"김상현"}}}}}