{"data":{"teamsInfo":{"away":{"hr":[],"hit":[18,61,110,115,121,174,177,192,198,256,271,383,394,400],"o":[5,12,22,66,73,131,146,188,207,215,263,283,310,320,323,379,437,443,451,488,492,497],"lineup":{"71837":{"balls":[115,198,320,451],"name":"김강민"},"75808":{"balls":[5,121,207,323,488],"name":"정근우"},"62895":{"balls":[61,174,394],"name":"한동민"},"60891":{"balls":[66,177],"name":"조성우"},"71857":{"balls":[271,400],"name":"박재상"},"96307":{"balls":[73,188,283,437],"name":"박진만"},"75847":{"balls":[18,256,383,497],"name":"최정"},"76802":{"balls":[12,131,215,379,492],"name":"김성현"},"98144":{"balls":[110,192,310,443],"name":"조인성"},"70646":{"balls":[22,146,263],"name":"김상현"}}},"home":{"hr":[],"hit":[43,49,87,96,240,331,361,415,422,467,503,507],"o":[29,36,56,80,90,103,152,168,231,235,251,292,298,302,341,349,367,412,431,459,474,478,515,522,525],"lineup":{"73342":{"balls":[43,302,422,522],"name":"이택근"},"78168":{"balls":[29,103,292,412,507],"name":"서건창"},"77243":{"balls":[503],"name":"허도환"},"77564":{"balls":[90,240,361,478],"name":"김민성"},"74339":{"balls":[87,235,474],"name":"유한준"},"70312":{"balls":[349,467],"name":"오윤"},"73136":{"balls":[80,231],"name":"이성열"},"79365":{"balls":[96,251],"name":"박동원"},"75125":{"balls":[49,168,331,431,525],"name":"박병호"},"76325":{"balls":[56,341,459],"name":"강정호"},"72303":{"balls":[367],"name":"김민우"},"71347":{"balls":[36,152,298,415,515],"name":"장기영"}}}},"ballsInfo":{"away":{"207":{"inn":"4회초","detailResult":"3루수 땅볼 아웃","result":"아웃","seqno":207,"gy":390,"batterName":"정근우","gx":202,"pitcherName":"밴헤켄"},"5":{"inn":"1회초","detailResult":"유격수 땅볼 아웃","result":"아웃","seqno":5,"gy":343,"batterName":"정근우","gx":215,"pitcherName":"밴헤켄"},"66":{"inn":"2회초","detailResult":"삼진 아웃","result":"아웃","seqno":66,"gy":0,"batterName":"조성우","gx":0,"pitcherName":"밴헤켄"},"283":{"inn":"5회초","detailResult":"3루수 땅볼 아웃","result":"아웃","seqno":283,"gy":384,"batterName":"박진만","gx":182,"pitcherName":"밴헤켄"},"400":{"inn":"7회초","detailResult":"투수 앞 땅볼로 출루","result":"안타","seqno":400,"gy":392,"batterName":"박재상","gx":258,"pitcherName":"박성훈"},"131":{"inn":"3회초","detailResult":"2루수 병살타 아웃","result":"아웃","seqno":131,"gy":326,"batterName":"김성현","gx":275,"pitcherName":"밴헤켄"},"198":{"inn":"4회초","detailResult":"우익수 오른쪽 2루타","result":"안타","seqno":198,"gy":237,"batterName":"김강민","gx":461,"pitcherName":"밴헤켄"},"12":{"inn":"1회초","detailResult":"유격수 땅볼 아웃","result":"아웃","seqno":12,"gy":348,"batterName":"김성현","gx":218,"pitcherName":"밴헤켄"},"73":{"inn":"2회초","detailResult":"유격수 병살타 아웃","result":"아웃","seqno":73,"gy":342,"batterName":"박진만","gx":216,"pitcherName":"밴헤켄"},"192":{"inn":"4회초","detailResult":"우중간 2루타","result":"안타","seqno":192,"gy":171,"batterName":"조인성","gx":406,"pitcherName":"밴헤켄"},"394":{"inn":"7회초","detailResult":"우익수 오른쪽 1루타","result":"안타","seqno":394,"gy":252,"batterName":"한동민","gx":421,"pitcherName":"박성훈"},"256":{"inn":"5회초","detailResult":"중견수 뒤 2루타","result":"안타","seqno":256,"gy":130,"batterName":"최정","gx":290,"pitcherName":"밴헤켄"},"18":{"inn":"1회초","detailResult":"중견수 왼쪽 1루타","result":"안타","seqno":18,"gy":282,"batterName":"최정","gx":197,"pitcherName":"밴헤켄"},"323":{"inn":"6회초","detailResult":"중견수 플라이 아웃","result":"아웃","seqno":323,"gy":196,"batterName":"정근우","gx":241,"pitcherName":"이보근"},"263":{"inn":"5회초","detailResult":"삼진 아웃","result":"아웃","seqno":263,"gy":0,"batterName":"김상현","gx":0,"pitcherName":"밴헤켄"},"320":{"inn":"6회초","detailResult":"유격수 땅볼 아웃","result":"아웃","seqno":320,"gy":337,"batterName":"김강민","gx":220,"pitcherName":"이보근"},"22":{"inn":"1회초","detailResult":"2루수 땅볼 아웃","result":"아웃","seqno":22,"gy":338,"batterName":"김상현","gx":295,"pitcherName":"밴헤켄"},"146":{"inn":"3회초","detailResult":"삼진 아웃","result":"아웃","seqno":146,"gy":0,"batterName":"김상현","gx":0,"pitcherName":"밴헤켄"},"215":{"inn":"4회초","detailResult":"유격수 땅볼 아웃","result":"아웃","seqno":215,"gy":334,"batterName":"김성현","gx":220,"pitcherName":"밴헤켄"},"451":{"inn":"8회초","detailResult":"좌익수 플라이 아웃","result":"아웃","seqno":451,"gy":227,"batterName":"김강민","gx":118,"pitcherName":"마정길"},"271":{"inn":"5회초","detailResult":"유격수 앞 땅볼로 출루","result":"안타","seqno":271,"gy":345,"batterName":"박재상","gx":214,"pitcherName":"밴헤켄"},"443":{"inn":"8회초","detailResult":"3루수 땅볼 아웃","result":"아웃","seqno":443,"gy":403,"batterName":"조인성","gx":203,"pitcherName":"마정길"},"174":{"inn":"4회초","detailResult":"중견수 앞 1루타","result":"안타","seqno":174,"gy":213,"batterName":"한동민","gx":261,"pitcherName":"밴헤켄"},"310":{"inn":"6회초","detailResult":"2루수 땅볼 아웃","result":"아웃","seqno":310,"gy":310,"batterName":"조인성","gx":261,"pitcherName":"이보근"},"110":{"inn":"3회초","detailResult":"중견수 뒤 2루타","result":"안타","seqno":110,"gy":127,"batterName":"조인성","gx":197,"pitcherName":"밴헤켄"},"383":{"inn":"7회초","detailResult":"좌익수 왼쪽 2루타","result":"안타","seqno":383,"gy":203,"batterName":"최정","gx":39,"pitcherName":"이보근"},"497":{"inn":"9회초","detailResult":"유격수 플라이 아웃","result":"아웃","seqno":497,"gy":260,"batterName":"최정","gx":202,"pitcherName":"마정길"},"437":{"inn":"8회초","detailResult":"우익수 파울플라이 아웃","result":"아웃","seqno":437,"gy":253,"batterName":"박진만","gx":444,"pitcherName":"마정길"},"379":{"inn":"7회초","detailResult":"중견수 플라이 아웃","result":"아웃","seqno":379,"gy":133,"batterName":"김성현","gx":275,"pitcherName":"이보근"},"492":{"inn":"9회초","detailResult":"좌익수 플라이 아웃","result":"아웃","seqno":492,"gy":226,"batterName":"김성현","gx":139,"pitcherName":"마정길"},"115":{"inn":"3회초","detailResult":"중견수 오른쪽 1루타","result":"안타","seqno":115,"gy":213,"batterName":"김강민","gx":272,"pitcherName":"밴헤켄"},"488":{"inn":"9회초","detailResult":"삼진 아웃","result":"아웃","seqno":488,"gy":0,"batterName":"정근우","gx":0,"pitcherName":"마정길"},"188":{"inn":"4회초","detailResult":"삼진 아웃","result":"아웃","seqno":188,"gy":0,"batterName":"박진만","gx":0,"pitcherName":"밴헤켄"},"177":{"inn":"4회초","detailResult":"우익수 오른쪽 1루타","result":"안타","seqno":177,"gy":248,"batterName":"조성우","gx":382,"pitcherName":"밴헤켄"},"121":{"inn":"3회초","detailResult":"중견수 앞 1루타","result":"안타","seqno":121,"gy":214,"batterName":"정근우","gx":242,"pitcherName":"밴헤켄"},"61":{"inn":"2회초","detailResult":"1루수 왼쪽 내야안타","result":"안타","seqno":61,"gy":348,"batterName":"한동민","gx":298,"pitcherName":"밴헤켄"}},"home":{"478":{"inn":"8회말","detailResult":"3루수 땅볼 아웃","result":"아웃","seqno":478,"gy":374,"batterName":"김민성","gx":194,"pitcherName":"전유수"},"341":{"inn":"6회말","detailResult":"투수 땅볼 아웃","result":"아웃","seqno":341,"gy":406,"batterName":"강정호","gx":265,"pitcherName":"세든"},"474":{"inn":"8회말","detailResult":"삼진 아웃","result":"아웃","seqno":474,"gy":0,"batterName":"유한준","gx":0,"pitcherName":"전유수"},"415":{"inn":"7회말","detailResult":"좌익수 왼쪽 1루타","result":"안타","seqno":415,"gy":273,"batterName":"장기영","gx":137,"pitcherName":"김준"},"412":{"inn":"7회말","detailResult":"2루수 땅볼 아웃","result":"아웃","seqno":412,"gy":343,"batterName":"서건창","gx":288,"pitcherName":"김준"},"349":{"inn":"6회말","detailResult":"삼진 아웃","result":"아웃","seqno":349,"gy":0,"batterName":"오윤","gx":0,"pitcherName":"세든"},"467":{"inn":"8회말","detailResult":"우익수 오른쪽 1루타","result":"안타","seqno":467,"gy":249,"batterName":"오윤","gx":411,"pitcherName":"전유수"},"152":{"inn":"3회말","detailResult":"3루수 땅볼 아웃","result":"아웃","seqno":152,"gy":397,"batterName":"장기영","gx":231,"pitcherName":"세든"},"87":{"inn":"2회말","detailResult":"좌익수 앞 1루타","result":"안타","seqno":87,"gy":257,"batterName":"유한준","gx":156,"pitcherName":"세든"},"459":{"inn":"8회말","detailResult":"삼진 아웃","result":"아웃","seqno":459,"gy":0,"batterName":"강정호","gx":0,"pitcherName":"전유수"},"80":{"inn":"2회말","detailResult":"삼진 아웃","result":"아웃","seqno":80,"gy":0,"batterName":"이성열","gx":0,"pitcherName":"세든"},"29":{"inn":"1회말","detailResult":"중견수 플라이 아웃","result":"아웃","seqno":29,"gy":196,"batterName":"서건창","gx":255,"pitcherName":"세든"},"331":{"inn":"6회말","detailResult":"좌익수 앞 1루타","result":"안타","seqno":331,"gy":239,"batterName":"박병호","gx":123,"pitcherName":"세든"},"90":{"inn":"2회말","detailResult":"좌익수 플라이 아웃","result":"아웃","seqno":90,"gy":262,"batterName":"김민성","gx":23,"pitcherName":"세든"},"103":{"inn":"2회말","detailResult":"좌익수 플라이 아웃","result":"아웃","seqno":103,"gy":223,"batterName":"서건창","gx":123,"pitcherName":"세든"},"168":{"inn":"3회말","detailResult":"삼진 아웃","result":"아웃","seqno":168,"gy":0,"batterName":"박병호","gx":0,"pitcherName":"세든"},"235":{"inn":"4회말","detailResult":"좌익수 플라이 아웃","result":"아웃","seqno":235,"gy":197,"batterName":"유한준","gx":125,"pitcherName":"세든"},"96":{"inn":"2회말","detailResult":"좌익수 앞 1루타","result":"안타","seqno":96,"gy":234,"batterName":"박동원","gx":127,"pitcherName":"세든"},"36":{"inn":"1회말","detailResult":"좌익수 플라이 아웃","result":"아웃","seqno":36,"gy":238,"batterName":"장기영","gx":149,"pitcherName":"세든"},"515":{"inn":"9회말","detailResult":"유격수 땅볼 아웃","result":"아웃","seqno":515,"gy":338,"batterName":"장기영","gx":221,"pitcherName":"박희수"},"507":{"inn":"9회말","detailResult":"우익수 앞 1루타","result":"안타","seqno":507,"gy":235,"batterName":"서건창","gx":364,"pitcherName":"박희수"},"231":{"inn":"4회말","detailResult":"삼진 아웃","result":"아웃","seqno":231,"gy":0,"batterName":"이성열","gx":0,"pitcherName":"세든"},"525":{"inn":"9회말","detailResult":"2루수 땅볼 아웃","result":"아웃","seqno":525,"gy":331,"batterName":"박병호","gx":278,"pitcherName":"박희수"},"43":{"inn":"1회말","detailResult":"우익수 앞 1루타","result":"안타","seqno":43,"gy":264,"batterName":"이택근","gx":388,"pitcherName":"세든"},"503":{"inn":"9회말","detailResult":"좌익수 앞 1루타","result":"안타","seqno":503,"gy":246,"batterName":"허도환","gx":127,"pitcherName":"박희수"},"522":{"inn":"9회말","detailResult":"3루수 땅볼 아웃","result":"아웃","seqno":522,"gy":393,"batterName":"이택근","gx":200,"pitcherName":"박희수"},"49":{"inn":"1회말","detailResult":"좌중간 2루타","result":"안타","seqno":49,"gy":160,"batterName":"박병호","gx":158,"pitcherName":"세든"},"292":{"inn":"5회말","detailResult":"포수 파울플라이 아웃","result":"아웃","seqno":292,"gy":472,"batterName":"서건창","gx":228,"pitcherName":"세든"},"251":{"inn":"4회말","detailResult":"포수 스트라이크 낫 아웃","result":"아웃","seqno":251,"gy":0,"batterName":"박동원","gx":0,"pitcherName":"세든"},"431":{"inn":"7회말","detailResult":"3루수 병살타 아웃","result":"아웃","seqno":431,"gy":374,"batterName":"박병호","gx":193,"pitcherName":"전유수"},"298":{"inn":"5회말","detailResult":"삼진 아웃","result":"아웃","seqno":298,"gy":0,"batterName":"장기영","gx":0,"pitcherName":"세든"},"56":{"inn":"1회말","detailResult":"삼진 아웃","result":"아웃","seqno":56,"gy":0,"batterName":"강정호","gx":0,"pitcherName":"세든"},"367":{"inn":"6회말","detailResult":"2루수 플라이 아웃","result":"아웃","seqno":367,"gy":354,"batterName":"김민우","gx":258,"pitcherName":"세든"},"361":{"inn":"6회말","detailResult":"좌익수 앞 1루타","result":"안타","seqno":361,"gy":255,"batterName":"김민성","gx":106,"pitcherName":"세든"},"240":{"inn":"4회말","detailResult":"우익수 앞 1루타","result":"안타","seqno":240,"gy":241,"batterName":"김민성","gx":358,"pitcherName":"세든"},"302":{"inn":"5회말","detailResult":"중견수 플라이 아웃","result":"아웃","seqno":302,"gy":262,"batterName":"이택근","gx":264,"pitcherName":"세든"},"422":{"inn":"7회말","detailResult":"우익수 앞 1루타","result":"안타","seqno":422,"gy":229,"batterName":"이택근","gx":361,"pitcherName":"전유수"}}}}}