{"data":{"teamsInfo":{"away":{"hr":[38],"hit":[6,20,32,52,73,93,139,182,188,193,200,306,322,331,376,464,468,473,526],"o":[83,90,99,132,143,149,213,256,262,268,297,315,372,385,482,520,538,608,620,633],"lineup":{"76267":{"balls":[90,188,306,464],"name":"최주환"},"71552":{"balls":[38,132,213,331],"name":"최준석"},"76249":{"balls":[6,83,182,297,608],"name":"민병헌"},"75566":{"balls":[385,538],"name":"이원석"},"79240":{"balls":[52,143,256,372,520],"name":"허경민"},"77248":{"balls":[482,633],"name":"오재원"},"73213":{"balls":[73,268],"name":"손시헌"},"76290":{"balls":[20,93,193,315,468],"name":"김현수"},"99222":{"balls":[32,99,200,322,473],"name":"홍성흔"},"99507":{"balls":[139],"name":"임재철"},"76232":{"balls":[149,262,376,526],"name":"양의지"},"62244":{"balls":[620],"name":"박세혁"}}},"home":{"hr":[116,552,638],"hit":[338,348,353,392,396,413,426,557,561,577,594,650,669],"o":[108,112,124,155,163,170,229,236,245,283,291,341,357,436,450,487,490,503,548,587,600,660],"lineup":{"75808":{"balls":[108,236,357],"name":"정근우"},"71837":{"balls":[245,392,490,587],"name":"김강민"},"71848":{"balls":[229,353,450],"name":"조동화"},"71857":{"balls":[163,338,426,552],"name":"박재상"},"75847":{"balls":[116,396],"name":"최정"},"76802":{"balls":[487,577,669],"name":"김성현"},"70646":{"balls":[124,283],"name":"김상현"},"60805":{"balls":[348,561,660],"name":"최윤석"},"62895":{"balls":[155,291,413,548,638],"name":"한동민"},"60891":{"balls":[503,600],"name":"조성우"},"96307":{"balls":[594],"name":"박진만"},"76849":{"balls":[112],"name":"이명기"},"98144":{"balls":[170],"name":"조인성"},"71842":{"balls":[341,436,557,650],"name":"정상호"}}}},"ballsInfo":{"away":{"608":{"inn":"9회초","detailResult":"2루수 플라이 아웃","result":"아웃","seqno":608,"gy":352,"batterName":"민병헌","gx":285,"pitcherName":"전유수"},"139":{"inn":"2회초","detailResult":"중견수 왼쪽 1루타","result":"안타","seqno":139,"gy":239,"batterName":"임재철","gx":194,"pitcherName":"백인식"},"200":{"inn":"3회초","detailResult":"좌익수 뒤 2루타","result":"안타","seqno":200,"gy":168,"batterName":"홍성흔","gx":96,"pitcherName":"백인식"},"143":{"inn":"2회초","detailResult":"2루수 라인드라이브 아웃","result":"아웃","seqno":143,"gy":347,"batterName":"허경민","gx":281,"pitcherName":"백인식"},"6":{"inn":"1회초","detailResult":"좌익수 뒤 2루타","result":"안타","seqno":6,"gy":158,"batterName":"민병헌","gx":97,"pitcherName":"여건욱"},"473":{"inn":"7회초","detailResult":"유격수 앞 땅볼로 출루","result":"안타","seqno":473,"gy":350,"batterName":"홍성흔","gx":223,"pitcherName":"진해수"},"468":{"inn":"7회초","detailResult":"중견수 앞 1루타","result":"안타","seqno":468,"gy":299,"batterName":"김현수","gx":269,"pitcherName":"진해수"},"193":{"inn":"3회초","detailResult":"우익수 앞 1루타","result":"안타","seqno":193,"gy":273,"batterName":"김현수","gx":357,"pitcherName":"백인식"},"132":{"inn":"2회초","detailResult":"삼진 아웃","result":"아웃","seqno":132,"gy":0,"batterName":"최준석","gx":0,"pitcherName":"백인식"},"73":{"inn":"1회초","detailResult":"3루수 앞 땅볼로 출루","result":"안타","seqno":73,"gy":399,"batterName":"손시헌","gx":216,"pitcherName":"최영필"},"620":{"inn":"9회초","detailResult":"1루수 땅볼 아웃","result":"아웃","seqno":620,"gy":388,"batterName":"박세혁","gx":306,"pitcherName":"전유수"},"464":{"inn":"7회초","detailResult":"중견수 앞 1루타","result":"안타","seqno":464,"gy":279,"batterName":"최주환","gx":253,"pitcherName":"진해수"},"256":{"inn":"4회초","detailResult":"중견수 플라이 아웃","result":"아웃","seqno":256,"gy":211,"batterName":"허경민","gx":279,"pitcherName":"백인식"},"322":{"inn":"5회초","detailResult":"우익수 앞 1루타","result":"안타","seqno":322,"gy":282,"batterName":"홍성흔","gx":335,"pitcherName":"백인식"},"262":{"inn":"4회초","detailResult":"삼진 아웃","result":"아웃","seqno":262,"gy":0,"batterName":"양의지","gx":0,"pitcherName":"백인식"},"20":{"inn":"1회초","detailResult":"우익수 앞 1루타","result":"안타","seqno":20,"gy":327,"batterName":"김현수","gx":318,"pitcherName":"여건욱"},"83":{"inn":"1회초","detailResult":"중견수 희생플라이 아웃","result":"아웃","seqno":83,"gy":149,"batterName":"민병헌","gx":230,"pitcherName":"최영필"},"93":{"inn":"1회초","detailResult":"우익수 앞 1루타","result":"안타","seqno":93,"gy":316,"batterName":"김현수","gx":312,"pitcherName":"최영필"},"213":{"inn":"3회초","detailResult":"삼진 아웃","result":"아웃","seqno":213,"gy":0,"batterName":"최준석","gx":0,"pitcherName":"백인식"},"633":{"inn":"9회초","detailResult":"좌익수 파울플라이 아웃","result":"아웃","seqno":633,"gy":283,"batterName":"오재원","gx":28,"pitcherName":"전유수"},"385":{"inn":"6회초","detailResult":"삼진 아웃","result":"아웃","seqno":385,"gy":0,"batterName":"이원석","gx":0,"pitcherName":"진해수"},"331":{"inn":"5회초","detailResult":"유격수 앞 땅볼로 출루","result":"안타","seqno":331,"gy":363,"batterName":"최준석","gx":228,"pitcherName":"백인식"},"149":{"inn":"2회초","detailResult":"삼진 아웃","result":"아웃","seqno":149,"gy":0,"batterName":"양의지","gx":0,"pitcherName":"백인식"},"268":{"inn":"4회초","detailResult":"1루수 파울플라이 아웃","result":"아웃","seqno":268,"gy":406,"batterName":"손시헌","gx":312,"pitcherName":"백인식"},"90":{"inn":"1회초","detailResult":"1루수 땅볼 아웃","result":"아웃","seqno":90,"gy":387,"batterName":"최주환","gx":303,"pitcherName":"최영필"},"372":{"inn":"6회초","detailResult":"우익수 플라이 아웃","result":"아웃","seqno":372,"gy":250,"batterName":"허경민","gx":343,"pitcherName":"진해수"},"32":{"inn":"1회초","detailResult":"중견수 앞 1루타","result":"안타","seqno":32,"gy":243,"batterName":"홍성흔","gx":250,"pitcherName":"여건욱"},"306":{"inn":"5회초","detailResult":"2루수 왼쪽 내야안타","result":"안타","seqno":306,"gy":340,"batterName":"최주환","gx":256,"pitcherName":"백인식"},"38":{"inn":"1회초","detailResult":"좌중간 홈런","result":"홈런","seqno":38,"gy":111,"batterName":"최준석","gx":148,"pitcherName":"여건욱"},"99":{"inn":"1회초","detailResult":"좌익수 플라이 아웃","result":"아웃","seqno":99,"gy":180,"batterName":"홍성흔","gx":104,"pitcherName":"최영필"},"526":{"inn":"8회초","detailResult":"우중간 2루타","result":"안타","seqno":526,"gy":165,"batterName":"양의지","gx":301,"pitcherName":"윤길현"},"315":{"inn":"5회초","detailResult":"좌익수 플라이 아웃","result":"아웃","seqno":315,"gy":248,"batterName":"김현수","gx":144,"pitcherName":"백인식"},"520":{"inn":"8회초","detailResult":"2루수 병살타 아웃","result":"아웃","seqno":520,"gy":359,"batterName":"허경민","gx":290,"pitcherName":"윤길현"},"376":{"inn":"6회초","detailResult":"유격수 앞 땅볼로 출루","result":"안타","seqno":376,"gy":355,"batterName":"양의지","gx":213,"pitcherName":"진해수"},"188":{"inn":"3회초","detailResult":"2루수 앞 땅볼로 출루","result":"안타","seqno":188,"gy":354,"batterName":"최주환","gx":278,"pitcherName":"백인식"},"52":{"inn":"1회초","detailResult":"중견수 앞 1루타","result":"안타","seqno":52,"gy":250,"batterName":"허경민","gx":246,"pitcherName":"최영필"},"297":{"inn":"5회초","detailResult":"투수 땅볼 아웃","result":"아웃","seqno":297,"gy":354,"batterName":"민병헌","gx":279,"pitcherName":"백인식"},"182":{"inn":"3회초","detailResult":"3루수 앞 땅볼로 출루","result":"안타","seqno":182,"gy":405,"batterName":"민병헌","gx":207,"pitcherName":"백인식"},"538":{"inn":"8회초","detailResult":"좌익수 플라이 아웃","result":"아웃","seqno":538,"gy":226,"batterName":"이원석","gx":145,"pitcherName":"윤길현"},"482":{"inn":"7회초","detailResult":"2루수 병살타 아웃","result":"아웃","seqno":482,"gy":354,"batterName":"오재원","gx":286,"pitcherName":"진해수"}},"home":{"548":{"inn":"8회말","detailResult":"좌익수 플라이 아웃","result":"아웃","seqno":548,"gy":267,"batterName":"한동민","gx":161,"pitcherName":"홍상삼"},"341":{"inn":"5회말","detailResult":"우익수 희생플라이 아웃","result":"아웃","seqno":341,"gy":195,"batterName":"정상호","gx":391,"pitcherName":"이정호"},"338":{"inn":"5회말","detailResult":"중견수 오른쪽 3루타","result":"안타","seqno":338,"gy":176,"batterName":"박재상","gx":324,"pitcherName":"이정호"},"413":{"inn":"6회말","detailResult":"우익수 앞 1루타","result":"안타","seqno":413,"gy":319,"batterName":"한동민","gx":324,"pitcherName":"이정호"},"283":{"inn":"4회말","detailResult":"3루수 병살타 아웃","result":"아웃","seqno":283,"gy":397,"batterName":"김상현","gx":209,"pitcherName":"이정호"},"557":{"inn":"8회말","detailResult":"유격수 오른쪽 내야안타","result":"안타","seqno":557,"gy":329,"batterName":"정상호","gx":242,"pitcherName":"변진수"},"348":{"inn":"5회말","detailResult":"좌익수 앞 1루타","result":"안타","seqno":348,"gy":348,"batterName":"최윤석","gx":186,"pitcherName":"이정호"},"552":{"inn":"8회말","detailResult":"우익수 뒤 홈런","result":"홈런","seqno":552,"gy":130,"batterName":"박재상","gx":404,"pitcherName":"홍상삼"},"155":{"inn":"2회말","detailResult":"삼진 아웃","result":"아웃","seqno":155,"gy":0,"batterName":"한동민","gx":0,"pitcherName":"이정호"},"392":{"inn":"6회말","detailResult":"중견수 앞 1루타","result":"안타","seqno":392,"gy":237,"batterName":"김강민","gx":274,"pitcherName":"이정호"},"561":{"inn":"8회말","detailResult":"우익수 앞 1루타","result":"안타","seqno":561,"gy":289,"batterName":"최윤석","gx":335,"pitcherName":"변진수"},"396":{"inn":"6회말","detailResult":"중견수 뒤 2루타","result":"안타","seqno":396,"gy":124,"batterName":"최정","gx":296,"pitcherName":"이정호"},"638":{"inn":"9회말","detailResult":"좌익수 뒤 홈런","result":"홈런","seqno":638,"gy":138,"batterName":"한동민","gx":88,"pitcherName":"오현택"},"450":{"inn":"6회말","detailResult":"좌익수 플라이 아웃","result":"아웃","seqno":450,"gy":250,"batterName":"조동화","gx":148,"pitcherName":"홍상삼"},"577":{"inn":"8회말","detailResult":"우중간 2루타","result":"안타","seqno":577,"gy":157,"batterName":"김성현","gx":324,"pitcherName":"변진수"},"170":{"inn":"2회말","detailResult":"우익수 파울플라이 아웃","result":"아웃","seqno":170,"gy":288,"batterName":"조인성","gx":466,"pitcherName":"이정호"},"236":{"inn":"3회말","detailResult":"삼진 아웃","result":"아웃","seqno":236,"gy":0,"batterName":"정근우","gx":0,"pitcherName":"이정호"},"650":{"inn":"9회말","detailResult":"좌익수 앞 1루타","result":"안타","seqno":650,"gy":274,"batterName":"정상호","gx":172,"pitcherName":"오현택"},"163":{"inn":"2회말","detailResult":"삼진 아웃","result":"아웃","seqno":163,"gy":0,"batterName":"박재상","gx":0,"pitcherName":"이정호"},"229":{"inn":"3회말","detailResult":"좌익수 플라이 아웃","result":"아웃","seqno":229,"gy":241,"batterName":"조동화","gx":128,"pitcherName":"이정호"},"108":{"inn":"1회말","detailResult":"유격수 땅볼 아웃","result":"아웃","seqno":108,"gy":384,"batterName":"정근우","gx":231,"pitcherName":"이정호"},"587":{"inn":"8회말","detailResult":"2루수 땅볼 아웃","result":"아웃","seqno":587,"gy":353,"batterName":"김강민","gx":286,"pitcherName":"김상현"},"503":{"inn":"7회말","detailResult":"삼진 아웃","result":"아웃","seqno":503,"gy":0,"batterName":"조성우","gx":0,"pitcherName":"홍상삼"},"436":{"inn":"6회말","detailResult":"2루수 병살타 아웃","result":"아웃","seqno":436,"gy":352,"batterName":"정상호","gx":285,"pitcherName":"홍상삼"},"669":{"inn":"9회말","detailResult":"좌익수 뒤 1루타","result":"안타","seqno":669,"gy":146,"batterName":"김성현","gx":131,"pitcherName":"오현택"},"357":{"inn":"5회말","detailResult":"중견수 플라이 아웃","result":"아웃","seqno":357,"gy":240,"batterName":"정근우","gx":224,"pitcherName":"이정호"},"594":{"inn":"8회말","detailResult":"좌익수 앞 1루타","result":"안타","seqno":594,"gy":307,"batterName":"박진만","gx":188,"pitcherName":"김상현"},"291":{"inn":"4회말","detailResult":"삼진 아웃","result":"아웃","seqno":291,"gy":0,"batterName":"한동민","gx":0,"pitcherName":"이정호"},"116":{"inn":"1회말","detailResult":"우중간 홈런","result":"홈런","seqno":116,"gy":110,"batterName":"최정","gx":364,"pitcherName":"이정호"},"426":{"inn":"6회말","detailResult":"우익수 오른쪽 1루타","result":"안타","seqno":426,"gy":276,"batterName":"박재상","gx":342,"pitcherName":"이정호"},"353":{"inn":"5회말","detailResult":"3루수 앞 땅볼로 출루","result":"안타","seqno":353,"gy":400,"batterName":"조동화","gx":202,"pitcherName":"이정호"},"112":{"inn":"1회말","detailResult":"유격수 플라이 아웃","result":"아웃","seqno":112,"gy":335,"batterName":"이명기","gx":227,"pitcherName":"이정호"},"490":{"inn":"7회말","detailResult":"1루수 파울플라이 아웃","result":"아웃","seqno":490,"gy":399,"batterName":"김강민","gx":350,"pitcherName":"홍상삼"},"660":{"inn":"9회말","detailResult":"삼진 아웃","result":"아웃","seqno":660,"gy":0,"batterName":"최윤석","gx":0,"pitcherName":"오현택"},"600":{"inn":"8회말","detailResult":"투수 땅볼 아웃","result":"아웃","seqno":600,"gy":408,"batterName":"조성우","gx":250,"pitcherName":"오현택"},"487":{"inn":"7회말","detailResult":"유격수 땅볼 아웃","result":"아웃","seqno":487,"gy":366,"batterName":"김성현","gx":224,"pitcherName":"홍상삼"},"245":{"inn":"3회말","detailResult":"2루수 땅볼 아웃","result":"아웃","seqno":245,"gy":359,"batterName":"김강민","gx":292,"pitcherName":"이정호"},"124":{"inn":"1회말","detailResult":"삼진 아웃","result":"아웃","seqno":124,"gy":0,"batterName":"김상현","gx":0,"pitcherName":"이정호"}}}}}