{"data":{"teamsInfo":{"away":{"hr":[365],"hit":[8,20,70,109,169,419,436],"o":[15,26,75,82,112,122,128,153,164,222,230,258,285,301,353,361,382,428,441,499,507,511],"lineup":{"73703":{"balls":[428],"name":"한상훈"},"98420":{"balls":[301],"name":"강동우"},"76435":{"balls":[82],"name":"이여상"},"71752":{"balls":[20,153,365],"name":"김태균"},"76720":{"balls":[436],"name":"정범모"},"76746":{"balls":[26],"name":"김태완"},"63722":{"balls":[109],"name":"한승택"},"72139":{"balls":[511],"name":"추승우"},"71610":{"balls":[112,222,441],"name":"김경언"},"78756":{"balls":[8,122,230,353,499],"name":"오선진"},"74729":{"balls":[75,169,285,419],"name":"최진행"},"74148":{"balls":[15,128,258,361,507],"name":"이학준"},"78745":{"balls":[70,164,382],"name":"정현석"}}},"home":{"hr":[],"hit":[32,453,457,522],"o":[37,57,62,90,97,104,133,140,144,188,192,198,238,244,248,318,327,390,404,410,467,474,487,526,534,540],"lineup":{"71835":{"balls":[90,198,522],"name":"조중근"},"70312":{"balls":[534],"name":"오윤"},"79365":{"balls":[104,244,410],"name":"박동원"},"75125":{"balls":[57,188],"name":"박병호"},"97350":{"balls":[37,144,318],"name":"정수성"},"72303":{"balls":[97,238],"name":"김민우"},"71347":{"balls":[453,540],"name":"장기영"},"61363":{"balls":[474],"name":"문우람"},"73306":{"balls":[526],"name":"지석훈"},"78168":{"balls":[32,140,457],"name":"서건창"},"73342":{"balls":[327],"name":"이택근"},"74339":{"balls":[62,192,390,487],"name":"유한준"},"73136":{"balls":[404],"name":"이성열"},"79356":{"balls":[467],"name":"박헌도"},"76304":{"balls":[133,248],"name":"신현철"}}}},"ballsInfo":{"away":{"70":{"inn":"2회초","detailResult":"우익수 앞 1루타","result":"안타","seqno":70,"gy":0,"batterName":"정현석","gx":0,"pitcherName":"강윤구"},"8":{"inn":"1회초","detailResult":"중견수 앞 1루타","result":"안타","seqno":8,"gy":0,"batterName":"오선진","gx":0,"pitcherName":"강윤구"},"128":{"inn":"3회초","detailResult":"2루수 땅볼 아웃","result":"아웃","seqno":128,"gy":0,"batterName":"이학준","gx":0,"pitcherName":"강윤구"},"285":{"inn":"6회초","detailResult":"우익수 희생플라이 아웃","result":"아웃","seqno":285,"gy":0,"batterName":"최진행","gx":0,"pitcherName":"김상수"},"75":{"inn":"2회초","detailResult":"유격수 병살타 아웃","result":"아웃","seqno":75,"gy":0,"batterName":"최진행","gx":0,"pitcherName":"강윤구"},"15":{"inn":"1회초","detailResult":"삼진 아웃","result":"아웃","seqno":15,"gy":0,"batterName":"이학준","gx":0,"pitcherName":"강윤구"},"258":{"inn":"6회초","detailResult":"3루수 땅볼 아웃","result":"아웃","seqno":258,"gy":0,"batterName":"이학준","gx":0,"pitcherName":"김상수"},"153":{"inn":"4회초","detailResult":"3루수 땅볼 아웃","result":"아웃","seqno":153,"gy":0,"batterName":"김태균","gx":0,"pitcherName":"강윤구"},"222":{"inn":"5회초","detailResult":"유격수 병살타 아웃","result":"아웃","seqno":222,"gy":0,"batterName":"김경언","gx":0,"pitcherName":"김상수"},"20":{"inn":"1회초","detailResult":"좌익수 앞 1루타","result":"안타","seqno":20,"gy":0,"batterName":"김태균","gx":0,"pitcherName":"강윤구"},"82":{"inn":"2회초","detailResult":"삼진 아웃","result":"아웃","seqno":82,"gy":0,"batterName":"이여상","gx":0,"pitcherName":"강윤구"},"26":{"inn":"1회초","detailResult":"좌익수 플라이 아웃","result":"아웃","seqno":26,"gy":0,"batterName":"김태완","gx":0,"pitcherName":"강윤구"},"441":{"inn":"8회초","detailResult":"2루수 땅볼 아웃","result":"아웃","seqno":441,"gy":0,"batterName":"김경언","gx":0,"pitcherName":"이보근"},"169":{"inn":"4회초","detailResult":"유격수 앞 땅볼로 출루","result":"안타","seqno":169,"gy":0,"batterName":"최진행","gx":0,"pitcherName":"강윤구"},"511":{"inn":"9회초","detailResult":"유격수 땅볼 아웃","result":"아웃","seqno":511,"gy":0,"batterName":"추승우","gx":0,"pitcherName":"문성현"},"507":{"inn":"9회초","detailResult":"투수 땅볼 아웃","result":"아웃","seqno":507,"gy":0,"batterName":"이학준","gx":0,"pitcherName":"문성현"},"230":{"inn":"5회초","detailResult":"중견수 플라이 아웃","result":"아웃","seqno":230,"gy":0,"batterName":"오선진","gx":0,"pitcherName":"김상수"},"109":{"inn":"3회초","detailResult":"유격수 왼쪽 내야안타","result":"안타","seqno":109,"gy":0,"batterName":"한승택","gx":0,"pitcherName":"강윤구"},"382":{"inn":"7회초","detailResult":"3루수 땅볼 아웃","result":"아웃","seqno":382,"gy":0,"batterName":"정현석","gx":0,"pitcherName":"조상우"},"436":{"inn":"8회초","detailResult":"2루수 왼쪽 내야안타","result":"안타","seqno":436,"gy":0,"batterName":"정범모","gx":0,"pitcherName":"이보근"},"499":{"inn":"9회초","detailResult":"3루수 땅볼 아웃","result":"아웃","seqno":499,"gy":0,"batterName":"오선진","gx":0,"pitcherName":"문성현"},"164":{"inn":"4회초","detailResult":"좌익수 플라이 아웃","result":"아웃","seqno":164,"gy":0,"batterName":"정현석","gx":0,"pitcherName":"강윤구"},"353":{"inn":"7회초","detailResult":"투수 땅볼 아웃","result":"아웃","seqno":353,"gy":0,"batterName":"오선진","gx":0,"pitcherName":"조상우"},"428":{"inn":"8회초","detailResult":"좌익수 플라이 아웃","result":"아웃","seqno":428,"gy":0,"batterName":"한상훈","gx":0,"pitcherName":"이보근"},"112":{"inn":"3회초","detailResult":"포수 희생번트 아웃","result":"아웃","seqno":112,"gy":0,"batterName":"김경언","gx":0,"pitcherName":"강윤구"},"365":{"inn":"7회초","detailResult":"우익수 뒤 홈런","result":"홈런","seqno":365,"gy":0,"batterName":"김태균","gx":0,"pitcherName":"조상우"},"419":{"inn":"8회초","detailResult":"중견수 왼쪽 1루타","result":"안타","seqno":419,"gy":0,"batterName":"최진행","gx":0,"pitcherName":"이보근"},"122":{"inn":"3회초","detailResult":"삼진 아웃","result":"아웃","seqno":122,"gy":0,"batterName":"오선진","gx":0,"pitcherName":"강윤구"},"301":{"inn":"6회초","detailResult":"1루수 땅볼 아웃","result":"아웃","seqno":301,"gy":0,"batterName":"강동우","gx":0,"pitcherName":"김상수"},"361":{"inn":"7회초","detailResult":"우익수 파울플라이 아웃","result":"아웃","seqno":361,"gy":0,"batterName":"이학준","gx":0,"pitcherName":"조상우"}},"home":{"410":{"inn":"7회말","detailResult":"삼진 아웃","result":"아웃","seqno":410,"gy":0,"batterName":"박동원","gx":0,"pitcherName":"김광수"},"474":{"inn":"8회말","detailResult":"중견수 플라이 아웃","result":"아웃","seqno":474,"gy":0,"batterName":"문우람","gx":0,"pitcherName":"송창식"},"140":{"inn":"3회말","detailResult":"3루수 플라이 아웃","result":"아웃","seqno":140,"gy":0,"batterName":"서건창","gx":0,"pitcherName":"김혁민"},"198":{"inn":"4회말","detailResult":"1루수 땅볼 아웃","result":"아웃","seqno":198,"gy":0,"batterName":"조중근","gx":0,"pitcherName":"김일엽"},"133":{"inn":"3회말","detailResult":"좌익수 플라이 아웃","result":"아웃","seqno":133,"gy":0,"batterName":"신현철","gx":0,"pitcherName":"김혁민"},"192":{"inn":"4회말","detailResult":"우익수 파울플라이 아웃","result":"아웃","seqno":192,"gy":0,"batterName":"유한준","gx":0,"pitcherName":"김일엽"},"467":{"inn":"8회말","detailResult":"유격수 땅볼 아웃","result":"아웃","seqno":467,"gy":0,"batterName":"박헌도","gx":0,"pitcherName":"송창식"},"404":{"inn":"7회말","detailResult":"삼진 아웃","result":"아웃","seqno":404,"gy":0,"batterName":"이성열","gx":0,"pitcherName":"김광수"},"327":{"inn":"6회말","detailResult":"투수 땅볼 아웃","result":"아웃","seqno":327,"gy":0,"batterName":"이택근","gx":0,"pitcherName":"김광수"},"457":{"inn":"8회말","detailResult":"우익수 오른쪽 1루타","result":"안타","seqno":457,"gy":0,"batterName":"서건창","gx":0,"pitcherName":"송창식"},"144":{"inn":"3회말","detailResult":"유격수 플라이 아웃","result":"아웃","seqno":144,"gy":0,"batterName":"정수성","gx":0,"pitcherName":"김혁민"},"453":{"inn":"8회말","detailResult":"우중간 3루타","result":"안타","seqno":453,"gy":0,"batterName":"장기영","gx":0,"pitcherName":"송창식"},"390":{"inn":"7회말","detailResult":"유격수 땅볼 아웃","result":"아웃","seqno":390,"gy":0,"batterName":"유한준","gx":0,"pitcherName":"김광수"},"90":{"inn":"2회말","detailResult":"3루수 플라이 아웃","result":"아웃","seqno":90,"gy":0,"batterName":"조중근","gx":0,"pitcherName":"김혁민"},"238":{"inn":"5회말","detailResult":"투수 땅볼 아웃","result":"아웃","seqno":238,"gy":0,"batterName":"김민우","gx":0,"pitcherName":"임기영"},"32":{"inn":"1회말","detailResult":"우익수 왼쪽 1루타","result":"안타","seqno":32,"gy":0,"batterName":"서건창","gx":0,"pitcherName":"김혁민"},"97":{"inn":"2회말","detailResult":"삼진 아웃","result":"아웃","seqno":97,"gy":0,"batterName":"김민우","gx":0,"pitcherName":"김혁민"},"37":{"inn":"1회말","detailResult":"1루수 땅볼 아웃","result":"아웃","seqno":37,"gy":0,"batterName":"정수성","gx":0,"pitcherName":"김혁민"},"526":{"inn":"9회말","detailResult":"투수 희생번트 아웃","result":"아웃","seqno":526,"gy":0,"batterName":"지석훈","gx":0,"pitcherName":"안승민"},"522":{"inn":"9회말","detailResult":"좌익수 오른쪽 1루타","result":"안타","seqno":522,"gy":0,"batterName":"조중근","gx":0,"pitcherName":"안승민"},"104":{"inn":"2회말","detailResult":"삼진 아웃","result":"아웃","seqno":104,"gy":0,"batterName":"박동원","gx":0,"pitcherName":"김혁민"},"318":{"inn":"6회말","detailResult":"중견수 플라이 아웃","result":"아웃","seqno":318,"gy":0,"batterName":"정수성","gx":0,"pitcherName":"이충호"},"534":{"inn":"9회말","detailResult":"삼진 아웃","result":"아웃","seqno":534,"gy":0,"batterName":"오윤","gx":0,"pitcherName":"안승민"},"188":{"inn":"4회말","detailResult":"1루수 플라이 아웃","result":"아웃","seqno":188,"gy":0,"batterName":"박병호","gx":0,"pitcherName":"김일엽"},"248":{"inn":"5회말","detailResult":"중견수 플라이 아웃","result":"아웃","seqno":248,"gy":0,"batterName":"신현철","gx":0,"pitcherName":"임기영"},"540":{"inn":"9회말","detailResult":"1루수 땅볼 아웃","result":"아웃","seqno":540,"gy":0,"batterName":"장기영","gx":0,"pitcherName":"안승민"},"487":{"inn":"8회말","detailResult":"삼진 아웃","result":"아웃","seqno":487,"gy":0,"batterName":"유한준","gx":0,"pitcherName":"송창식"},"57":{"inn":"1회말","detailResult":"유격수 땅볼 아웃","result":"아웃","seqno":57,"gy":0,"batterName":"박병호","gx":0,"pitcherName":"김혁민"},"244":{"inn":"5회말","detailResult":"삼진 아웃","result":"아웃","seqno":244,"gy":0,"batterName":"박동원","gx":0,"pitcherName":"임기영"},"62":{"inn":"1회말","detailResult":"3루수 파울플라이 아웃","result":"아웃","seqno":62,"gy":0,"batterName":"유한준","gx":0,"pitcherName":"김혁민"}}}}}